[
    {
        "id": 836727,
        "long_title": "天黑别出门",
        "share_url": "https://www.bilibili.com/bangumi/play/ep836727",
        "title": "1",
        "type": 0,
        "type_title": "正片",
        "stat": {
            "coin": 120235,
            "dm": 117346,
            "favorite": 149243,
            "like": 271339,
            "reply": 8769,
            "share": 27254,
            "view": 90874986
        }
    },
    {
        "id": 1112251,
        "long_title": "我是霸体",
        "share_url": "https://www.bilibili.com/bangumi/play/ep1112251",
        "title": "2",
        "type": 0,
        "type_title": "正片",
        "stat": {
            "coin": 53509,
            "dm": 45929,
            "favorite": 18866,
            "like": 94405,
            "reply": 2742,
            "share": 3658,
            "view": 24052131
        }
    },
    {
        "id": 1112253,
        "long_title": "小魔崽子",
        "share_url": "https://www.bilibili.com/bangumi/play/ep1112253",
        "title": "3",
        "type": 0,
        "type_title": "正片",
        "stat": {
            "coin": 43685,
            "dm": 24401,
            "favorite": 14147,
            "like": 79533,
            "reply": 1726,
            "share": 2345,
            "view": 22664826
        }
    },
    {
        "id": 1113172,
        "long_title": "黑暗将至",
        "share_url": "https://www.bilibili.com/bangumi/play/ep1113172",
        "title": "4",
        "type": 0,
        "type_title": "正片",
        "stat": {
            "coin": 43084,
            "dm": 23607,
            "favorite": 12292,
            "like": 72986,
            "reply": 1580,
            "share": 2225,
            "view": 21238534
        }
    },
    {
        "id": 1114406,
        "long_title": "红粉骷髅",
        "share_url": "https://www.bilibili.com/bangumi/play/ep1114406",
        "title": "5",
        "type": 0,
        "type_title": "正片",
        "stat": {
            "coin": 50120,
            "dm": 34461,
            "favorite": 12017,
            "like": 79362,
            "reply": 2258,
            "share": 2428,
            "view": 21227415
        }
    },
    {
        "id": 1114407,
        "long_title": "神魔共鸣",
        "share_url": "https://www.bilibili.com/bangumi/play/ep1114407",
        "title": "6",
        "type": 0,
        "type_title": "正片",
        "stat": {
            "coin": 125240,
            "dm": 29419,
            "favorite": 20649,
            "like": 137626,
            "reply": 1570,
            "share": 2021,
            "view": 21538072
        }
    },
    {
        "id": 1115673,
        "long_title": "三音破壁",
        "share_url": "https://www.bilibili.com/bangumi/play/ep1115673",
        "title": "7",
        "type": 0,
        "type_title": "正片",
        "stat": {
            "coin": 135904,
            "dm": 32526,
            "favorite": 26411,
            "like": 143575,
            "reply": 1711,
            "share": 1971,
            "view": 25810630
        }
    },
    {
        "id": 1115674,
        "long_title": "破心中神",
        "share_url": "https://www.bilibili.com/bangumi/play/ep1115674",
        "title": "8",
        "type": 0,
        "type_title": "正片",
        "stat": {
            "coin": 118109,
            "dm": 122656,
            "favorite": 23731,
            "like": 141392,
            "reply": 2138,
            "share": 2001,
            "view": 25316888
        }
    },
    {
        "id": 1115675,
        "long_title": "壁画寻古",
        "share_url": "https://www.bilibili.com/bangumi/play/ep1115675",
        "title": "9",
        "type": 0,
        "type_title": "正片",
        "stat": {
            "coin": 102912,
            "dm": 22784,
            "favorite": 17655,
            "like": 118931,
            "reply": 1834,
            "share": 1784,
            "view": 21730654
        }
    },
    {
        "id": 1115676,
        "long_title": "小骗子，大骗子",
        "share_url": "https://www.bilibili.com/bangumi/play/ep1115676",
        "title": "10",
        "type": 0,
        "type_title": "正片",
        "stat": {
            "coin": 96003,
            "dm": 89598,
            "favorite": 14436,
            "like": 105344,
            "reply": 1369,
            "share": 1481,
            "view": 20424520
        }
    },
    {
        "id": 1192425,
        "long_title": "漓江剑法",
        "share_url": "https://www.bilibili.com/bangumi/play/ep1192425",
        "title": "11",
        "type": 0,
        "type_title": "正片",
        "stat": {
            "coin": 95376,
            "dm": 45055,
            "favorite": 16470,
            "like": 110297,
            "reply": 1794,
            "share": 1824,
            "view": 21718691
        }
    },
    {
        "id": 1192426,
        "long_title": "魔印禅心",
        "share_url": "https://www.bilibili.com/bangumi/play/ep1192426",
        "title": "12",
        "type": 0,
        "type_title": "正片",
        "stat": {
            "coin": 54497,
            "dm": 26150,
            "favorite": 12060,
            "like": 81599,
            "reply": 1385,
            "share": 1604,
            "view": 22561668
        }
    },
    {
        "id": 1192427,
        "long_title": "深夜魅影",
        "share_url": "https://www.bilibili.com/bangumi/play/ep1192427",
        "title": "13",
        "type": 0,
        "type_title": "正片",
        "stat": {
            "coin": 72954,
            "dm": 19368,
            "favorite": 16760,
            "like": 101518,
            "reply": 1706,
            "share": 1659,
            "view": 26250710
        }
    },
    {
        "id": 1192428,
        "long_title": "涌江龙宫",
        "share_url": "https://www.bilibili.com/bangumi/play/ep1192428",
        "title": "14",
        "type": 0,
        "type_title": "正片",
        "stat": {
            "coin": 68742,
            "dm": 64108,
            "favorite": 13148,
            "like": 87775,
            "reply": 1695,
            "share": 1870,
            "view": 21431801
        }
    },
    {
        "id": 1192429,
        "long_title": "太子少保",
        "share_url": "https://www.bilibili.com/bangumi/play/ep1192429",
        "title": "15",
        "type": 0,
        "type_title": "正片",
        "stat": {
            "coin": 57708,
            "dm": 25487,
            "favorite": 10368,
            "like": 75284,
            "reply": 1554,
            "share": 1189,
            "view": 15716284
        }
    },
    {
        "id": 1192430,
        "long_title": "三百六十堂",
        "share_url": "https://www.bilibili.com/bangumi/play/ep1192430",
        "title": "16",
        "type": 0,
        "type_title": "正片",
        "stat": {
            "coin": 57318,
            "dm": 24262,
            "favorite": 10547,
            "like": 75217,
            "reply": 1737,
            "share": 1217,
            "view": 16122587
        }
    },
    {
        "id": 1192431,
        "long_title": "少教主",
        "share_url": "https://www.bilibili.com/bangumi/play/ep1192431",
        "title": "17",
        "type": 0,
        "type_title": "正片",
        "stat": {
            "coin": 61533,
            "dm": 36179,
            "favorite": 13859,
            "like": 84292,
            "reply": 2494,
            "share": 1558,
            "view": 18177612
        }
    },
    {
        "id": 1192432,
        "long_title": "冰潮",
        "share_url": "https://www.bilibili.com/bangumi/play/ep1192432",
        "title": "18",
        "type": 0,
        "type_title": "正片",
        "stat": {
            "coin": 78049,
            "dm": 24960,
            "favorite": 18199,
            "like": 102325,
            "reply": 4108,
            "share": 1939,
            "view": 20919270
        }
    },
    {
        "id": 1192433,
        "long_title": "残老挑江山",
        "share_url": "https://www.bilibili.com/bangumi/play/ep1192433",
        "title": "19",
        "type": 0,
        "type_title": "正片",
        "stat": {
            "coin": 62780,
            "dm": 23420,
            "favorite": 10592,
            "like": 76379,
            "reply": 2304,
            "share": 1494,
            "view": 15609984
        }
    },
    {
        "id": 1192445,
        "long_title": "不夜城",
        "share_url": "https://www.bilibili.com/bangumi/play/ep1192445",
        "title": "20",
        "type": 0,
        "type_title": "正片",
        "stat": {
            "coin": 65643,
            "dm": 31362,
            "favorite": 12192,
            "like": 81642,
            "reply": 3155,
            "share": 1567,
            "view": 15482699
        }
    },
    {
        "id": 1192446,
        "long_title": "杀了令郎偿饭钱",
        "share_url": "https://www.bilibili.com/bangumi/play/ep1192446",
        "title": "21",
        "type": 0,
        "type_title": "正片",
        "stat": {
            "coin": 65437,
            "dm": 50692,
            "favorite": 11828,
            "like": 80142,
            "reply": 3139,
            "share": 1640,
            "view": 15524842
        }
    },
    {
        "id": 1192447,
        "long_title": "延康大军",
        "share_url": "https://www.bilibili.com/bangumi/play/ep1192447",
        "title": "22",
        "type": 0,
        "type_title": "正片",
        "stat": {
            "coin": 71874,
            "dm": 56129,
            "favorite": 12344,
            "like": 84206,
            "reply": 2796,
            "share": 1724,
            "view": 15250775
        }
    },
    {
        "id": 1192448,
        "long_title": "天图太子",
        "share_url": "https://www.bilibili.com/bangumi/play/ep1192448",
        "title": "23",
        "type": 0,
        "type_title": "正片",
        "stat": {
            "coin": 84402,
            "dm": 51375,
            "favorite": 14507,
            "like": 95704,
            "reply": 3261,
            "share": 1954,
            "view": 15432833
        }
    },
    {
        "id": 1192450,
        "long_title": "太阳船",
        "share_url": "https://www.bilibili.com/bangumi/play/ep1192450",
        "title": "24",
        "type": 0,
        "type_title": "正片",
        "stat": {
            "coin": 72316,
            "dm": 27979,
            "favorite": 11276,
            "like": 83631,
            "reply": 3341,
            "share": 1550,
            "view": 14641560
        }
    },
    {
        "id": 1192451,
        "long_title": "牧日者",
        "share_url": "https://www.bilibili.com/bangumi/play/ep1192451",
        "title": "25",
        "type": 0,
        "type_title": "正片",
        "stat": {
            "coin": 58028,
            "dm": 60299,
            "favorite": 9109,
            "like": 71275,
            "reply": 2861,
            "share": 1151,
            "view": 13263095
        }
    },
    {
        "id": 1192470,
        "long_title": "暗界",
        "share_url": "https://www.bilibili.com/bangumi/play/ep1192470",
        "title": "26",
        "type": 0,
        "type_title": "正片",
        "stat": {
            "coin": 65614,
            "dm": 57282,
            "favorite": 10249,
            "like": 77490,
            "reply": 2396,
            "share": 1436,
            "view": 14330528
        }
    },
    {
        "id": 1524209,
        "long_title": "死者生界",
        "share_url": "https://www.bilibili.com/bangumi/play/ep1524209",
        "title": "27",
        "type": 0,
        "type_title": "正片",
        "stat": {
            "coin": 63417,
            "dm": 35952,
            "favorite": 10088,
            "like": 77526,
            "reply": 2147,
            "share": 1184,
            "view": 14847246
        }
    },
    {
        "id": 1524210,
        "long_title": "天魔众",
        "share_url": "https://www.bilibili.com/bangumi/play/ep1524210",
        "title": "28",
        "type": 0,
        "type_title": "正片",
        "stat": {
            "coin": 50988,
            "dm": 38018,
            "favorite": 9523,
            "like": 63437,
            "reply": 1820,
            "share": 1036,
            "view": 14011818
        }
    },
    {
        "id": 1524211,
        "long_title": "斩魍魉",
        "share_url": "https://www.bilibili.com/bangumi/play/ep1524211",
        "title": "29",
        "type": 0,
        "type_title": "正片",
        "stat": {
            "coin": 44467,
            "dm": 41960,
            "favorite": 7217,
            "like": 57306,
            "reply": 1732,
            "share": 898,
            "view": 13529503
        }
    },
    {
        "id": 1524212,
        "long_title": "月亮守",
        "share_url": "https://www.bilibili.com/bangumi/play/ep1524212",
        "title": "30",
        "type": 0,
        "type_title": "正片",
        "stat": {
            "coin": 41417,
            "dm": 20517,
            "favorite": 6473,
            "like": 54672,
            "reply": 1368,
            "share": 754,
            "view": 12219230
        }
    },
    {
        "id": 1524213,
        "long_title": "破关行",
        "share_url": "https://www.bilibili.com/bangumi/play/ep1524213",
        "title": "31",
        "type": 0,
        "type_title": "正片",
        "stat": {
            "coin": 42189,
            "dm": 33342,
            "favorite": 6331,
            "like": 54176,
            "reply": 1241,
            "share": 731,
            "view": 12386105
        }
    },
    {
        "id": 1524214,
        "long_title": "剑履山河",
        "share_url": "https://www.bilibili.com/bangumi/play/ep1524214",
        "title": "32",
        "type": 0,
        "type_title": "正片",
        "stat": {
            "coin": 52735,
            "dm": 39319,
            "favorite": 8873,
            "like": 66446,
            "reply": 2049,
            "share": 1034,
            "view": 12204481
        }
    },
    {
        "id": 1524215,
        "long_title": "密水关",
        "share_url": "https://www.bilibili.com/bangumi/play/ep1524215",
        "title": "33",
        "type": 0,
        "type_title": "正片",
        "stat": {
            "coin": 48308,
            "dm": 34419,
            "favorite": 7621,
            "like": 61243,
            "reply": 1497,
            "share": 690,
            "view": 12155127
        }
    },
    {
        "id": 1524216,
        "long_title": "尸仙教",
        "share_url": "https://www.bilibili.com/bangumi/play/ep1524216",
        "title": "34",
        "type": 0,
        "type_title": "正片",
        "stat": {
            "coin": 46369,
            "dm": 59188,
            "favorite": 8589,
            "like": 60120,
            "reply": 2187,
            "share": 752,
            "view": 12879098
        }
    },
    {
        "id": 1524217,
        "long_title": "红尸蟞",
        "share_url": "https://www.bilibili.com/bangumi/play/ep1524217",
        "title": "35",
        "type": 0,
        "type_title": "正片",
        "stat": {
            "coin": 40515,
            "dm": 33329,
            "favorite": 6092,
            "like": 51710,
            "reply": 1961,
            "share": 576,
            "view": 11063619
        }
    },
    {
        "id": 1524218,
        "long_title": "坏蛋出村",
        "share_url": "https://www.bilibili.com/bangumi/play/ep1524218",
        "title": "36",
        "type": 0,
        "type_title": "正片",
        "stat": {
            "coin": 139022,
            "dm": 38567,
            "favorite": 22646,
            "like": 130108,
            "reply": 3214,
            "share": 793,
            "view": 11812769
        }
    },
    {
        "id": 1524219,
        "long_title": "驭龙门",
        "share_url": "https://www.bilibili.com/bangumi/play/ep1524219",
        "title": "37",
        "type": 0,
        "type_title": "正片",
        "stat": {
            "coin": 94377,
            "dm": 40652,
            "favorite": 15063,
            "like": 98970,
            "reply": 3702,
            "share": 820,
            "view": 12229288
        }
    },
    {
        "id": 1524220,
        "long_title": "水上天魔舞",
        "share_url": "https://www.bilibili.com/bangumi/play/ep1524220",
        "title": "38",
        "type": 0,
        "type_title": "正片",
        "stat": {
            "coin": 89521,
            "dm": 85037,
            "favorite": 15782,
            "like": 95314,
            "reply": 3232,
            "share": 799,
            "view": 12399918
        }
    },
    {
        "id": 1524221,
        "long_title": "太学院大考",
        "share_url": "https://www.bilibili.com/bangumi/play/ep1524221",
        "title": "39",
        "type": 0,
        "type_title": "正片",
        "stat": {
            "coin": 82340,
            "dm": 42490,
            "favorite": 12322,
            "like": 86823,
            "reply": 3266,
            "share": 723,
            "view": 11194288
        }
    },
    {
        "id": 1524222,
        "long_title": "延丰帝",
        "share_url": "https://www.bilibili.com/bangumi/play/ep1524222",
        "title": "40",
        "type": 0,
        "type_title": "正片",
        "stat": {
            "coin": 79450,
            "dm": 130478,
            "favorite": 12996,
            "like": 88882,
            "reply": 3851,
            "share": 821,
            "view": 12454515
        }
    },
    {
        "id": 1524223,
        "long_title": "祖师大考",
        "share_url": "https://www.bilibili.com/bangumi/play/ep1524223",
        "title": "41",
        "type": 0,
        "type_title": "正片",
        "stat": {
            "coin": 71292,
            "dm": 48118,
            "favorite": 11368,
            "like": 79123,
            "reply": 3208,
            "share": 651,
            "view": 10838854
        }
    },
    {
        "id": 1524224,
        "long_title": "千机毒",
        "share_url": "https://www.bilibili.com/bangumi/play/ep1524224",
        "title": "42",
        "type": 0,
        "type_title": "正片",
        "stat": {
            "coin": 73422,
            "dm": 65297,
            "favorite": 11947,
            "like": 86214,
            "reply": 3344,
            "share": 749,
            "view": 11744006
        }
    },
    {
        "id": 1524225,
        "long_title": "三大高手",
        "share_url": "https://www.bilibili.com/bangumi/play/ep1524225",
        "title": "43",
        "type": 0,
        "type_title": "正片",
        "stat": {
            "coin": 67111,
            "dm": 49016,
            "favorite": 9953,
            "like": 76797,
            "reply": 3079,
            "share": 603,
            "view": 10724280
        }
    },
    {
        "id": 1524226,
        "long_title": "道门堵门",
        "share_url": "https://www.bilibili.com/bangumi/play/ep1524226",
        "title": "44",
        "type": 0,
        "type_title": "正片",
        "stat": {
            "coin": 76296,
            "dm": 51334,
            "favorite": 10242,
            "like": 80012,
            "reply": 3472,
            "share": 636,
            "view": 10235029
        }
    },
    {
        "id": 1524227,
        "long_title": "绕剑式",
        "share_url": "https://www.bilibili.com/bangumi/play/ep1524227",
        "title": "45",
        "type": 0,
        "type_title": "正片",
        "stat": {
            "coin": 65898,
            "dm": 41565,
            "favorite": 9368,
            "like": 73831,
            "reply": 3252,
            "share": 601,
            "view": 9931003
        }
    },
    {
        "id": 1524228,
        "long_title": "少教主与道子",
        "share_url": "https://www.bilibili.com/bangumi/play/ep1524228",
        "title": "46",
        "type": 0,
        "type_title": "正片",
        "stat": {
            "coin": 74148,
            "dm": 51864,
            "favorite": 10482,
            "like": 80051,
            "reply": 3653,
            "share": 876,
            "view": 10327819
        }
    },
    {
        "id": 1524229,
        "long_title": "禅宗禅子",
        "share_url": "https://www.bilibili.com/bangumi/play/ep1524229",
        "title": "47",
        "type": 0,
        "type_title": "正片",
        "stat": {
            "coin": 61253,
            "dm": 36492,
            "favorite": 9582,
            "like": 70215,
            "reply": 3131,
            "share": 653,
            "view": 10306459
        }
    },
    {
        "id": 1524230,
        "long_title": "麻翻太学院",
        "share_url": "https://www.bilibili.com/bangumi/play/ep1524230",
        "title": "48",
        "type": 0,
        "type_title": "正片",
        "stat": {
            "coin": 61833,
            "dm": 34056,
            "favorite": 8892,
            "like": 70076,
            "reply": 2867,
            "share": 615,
            "view": 9796530
        }
    },
    {
        "id": 1524231,
        "long_title": "师兄师弟",
        "share_url": "https://www.bilibili.com/bangumi/play/ep1524231",
        "title": "49",
        "type": 0,
        "type_title": "正片",
        "stat": {
            "coin": 66159,
            "dm": 42060,
            "favorite": 10468,
            "like": 74611,
            "reply": 3154,
            "share": 702,
            "view": 10012832
        }
    },
    {
        "id": 1524232,
        "long_title": "武可汗",
        "share_url": "https://www.bilibili.com/bangumi/play/ep1524232",
        "title": "50",
        "type": 0,
        "type_title": "正片",
        "stat": {
            "coin": 69171,
            "dm": 45422,
            "favorite": 10958,
            "like": 77241,
            "reply": 3016,
            "share": 896,
            "view": 9430577
        }
    },
    {
        "id": 1524233,
        "long_title": "楼兰黄金宫",
        "share_url": "https://www.bilibili.com/bangumi/play/ep1524233",
        "title": "51",
        "type": 0,
        "type_title": "正片",
        "stat": {
            "coin": 60630,
            "dm": 40045,
            "favorite": 9130,
            "like": 69694,
            "reply": 2997,
            "share": 762,
            "view": 10046542
        }
    },
    {
        "id": 1524234,
        "long_title": "我，霸体",
        "share_url": "https://www.bilibili.com/bangumi/play/ep1524234",
        "title": "52",
        "type": 0,
        "type_title": "正片",
        "stat": {
            "coin": 63815,
            "dm": 40994,
            "favorite": 9205,
            "like": 69625,
            "reply": 3597,
            "share": 768,
            "view": 9700641
        }
    },
    {
        "id": 1524235,
        "long_title": "麻翻黄金宫",
        "share_url": "https://www.bilibili.com/bangumi/play/ep1524235",
        "title": "53",
        "type": 0,
        "type_title": "正片",
        "stat": {
            "coin": 64583,
            "dm": 39281,
            "favorite": 9289,
            "like": 69482,
            "reply": 3211,
            "share": 731,
            "view": 9392951
        }
    },
    {
        "id": 1524236,
        "long_title": "天可汗",
        "share_url": "https://www.bilibili.com/bangumi/play/ep1524236",
        "title": "54",
        "type": 0,
        "type_title": "正片",
        "stat": {
            "coin": 121415,
            "dm": 65367,
            "favorite": 18028,
            "like": 112955,
            "reply": 3310,
            "share": 848,
            "view": 10517049
        }
    },
    {
        "id": 1524237,
        "long_title": "转世圣童",
        "share_url": "https://www.bilibili.com/bangumi/play/ep1524237",
        "title": "55",
        "type": 0,
        "type_title": "正片",
        "stat": {
            "coin": 75667,
            "dm": 29222,
            "favorite": 10860,
            "like": 79123,
            "reply": 3188,
            "share": 719,
            "view": 10022103
        }
    },
    {
        "id": 1524238,
        "long_title": "圣教主登基",
        "share_url": "https://www.bilibili.com/bangumi/play/ep1524238",
        "title": "56",
        "type": 0,
        "type_title": "正片",
        "stat": {
            "coin": 75586,
            "dm": 42405,
            "favorite": 11419,
            "like": 79478,
            "reply": 3277,
            "share": 766,
            "view": 9557446
        }
    },
    {
        "id": 1524239,
        "long_title": "功法大一统",
        "share_url": "https://www.bilibili.com/bangumi/play/ep1524239",
        "title": "57",
        "type": 0,
        "type_title": "正片",
        "stat": {
            "coin": 61105,
            "dm": 66916,
            "favorite": 8826,
            "like": 67460,
            "reply": 2798,
            "share": 641,
            "view": 9547057
        }
    },
    {
        "id": 1524240,
        "long_title": "虫军",
        "share_url": "https://www.bilibili.com/bangumi/play/ep1524240",
        "title": "58",
        "type": 0,
        "type_title": "正片",
        "stat": {
            "coin": 59076,
            "dm": 24295,
            "favorite": 7901,
            "like": 63081,
            "reply": 2908,
            "share": 524,
            "view": 8693308
        }
    },
    {
        "id": 1524241,
        "long_title": "知行合一",
        "share_url": "https://www.bilibili.com/bangumi/play/ep1524241",
        "title": "59",
        "type": 0,
        "type_title": "正片",
        "stat": {
            "coin": 57160,
            "dm": 18313,
            "favorite": 8041,
            "like": 61554,
            "reply": 2951,
            "share": 615,
            "view": 8447573
        }
    },
    {
        "id": 1524242,
        "long_title": "阴间突袭",
        "share_url": "https://www.bilibili.com/bangumi/play/ep1524242",
        "title": "60",
        "type": 0,
        "type_title": "正片",
        "stat": {
            "coin": 59587,
            "dm": 24018,
            "favorite": 9503,
            "like": 63848,
            "reply": 3092,
            "share": 692,
            "view": 9199785
        }
    },
    {
        "id": 1524243,
        "long_title": "调鬼遣神",
        "share_url": "https://www.bilibili.com/bangumi/play/ep1524243",
        "title": "61",
        "type": 0,
        "type_title": "正片",
        "stat": {
            "coin": 52295,
            "dm": 21297,
            "favorite": 7183,
            "like": 54643,
            "reply": 3105,
            "share": 476,
            "view": 7847351
        }
    },
    {
        "id": 1524244,
        "long_title": "都天魔王",
        "share_url": "https://www.bilibili.com/bangumi/play/ep1524244",
        "title": "62",
        "type": 0,
        "type_title": "正片",
        "stat": {
            "coin": 53893,
            "dm": 24760,
            "favorite": 10009,
            "like": 62446,
            "reply": 3491,
            "share": 623,
            "view": 8847827
        }
    },
    {
        "id": 1524245,
        "long_title": "血祭",
        "share_url": "https://www.bilibili.com/bangumi/play/ep1524245",
        "title": "63",
        "type": 0,
        "type_title": "正片",
        "stat": {
            "coin": 62670,
            "dm": 64020,
            "favorite": 9406,
            "like": 65404,
            "reply": 3411,
            "share": 802,
            "view": 8970829
        }
    },
    {
        "id": 1524246,
        "long_title": "两条路",
        "share_url": "https://www.bilibili.com/bangumi/play/ep1524246",
        "title": "64",
        "type": 0,
        "type_title": "正片",
        "stat": {
            "coin": 51670,
            "dm": 17887,
            "favorite": 6936,
            "like": 54881,
            "reply": 2855,
            "share": 497,
            "view": 7106116
        }
    },
    {
        "id": 1524247,
        "long_title": "强者如云",
        "share_url": "https://www.bilibili.com/bangumi/play/ep1524247",
        "title": "65",
        "type": 0,
        "type_title": "正片",
        "stat": {
            "coin": 83788,
            "dm": 21502,
            "favorite": 12283,
            "like": 76007,
            "reply": 3241,
            "share": 596,
            "view": 7482844
        }
    },
    {
        "id": 1524248,
        "long_title": "天魔教威",
        "share_url": "https://www.bilibili.com/bangumi/play/ep1524248",
        "title": "66",
        "type": 0,
        "type_title": "正片",
        "stat": {
            "coin": 82235,
            "dm": 23355,
            "favorite": 11735,
            "like": 76002,
            "reply": 3806,
            "share": 1042,
            "view": 6780856
        }
    },
    {
        "id": 1524249,
        "long_title": "君臣之心",
        "share_url": "https://www.bilibili.com/bangumi/play/ep1524249",
        "title": "67",
        "type": 0,
        "type_title": "正片",
        "stat": {
            "coin": 54409,
            "dm": 17543,
            "favorite": 7585,
            "like": 55833,
            "reply": 3208,
            "share": 422,
            "view": 4851342
        }
    },
    {
        "id": 2756445,
        "long_title": "这一剑，有着冲破时代的锋芒！",
        "share_url": "https://www.bilibili.com/bangumi/play/ep2756445",
        "title": "南疆平叛篇终战预热PV",
        "type": 1,
        "type_title": "预告",
        "stat": {
            "coin": 1340,
            "dm": 80,
            "favorite": 463,
            "like": 3898,
            "reply": 320,
            "share": 88,
            "view": 1197750
        }
    },
    {
        "id": 2656487,
        "long_title": "荧惑星君形态&镇星君形态",
        "share_url": "https://www.bilibili.com/bangumi/play/ep2656487",
        "title": "秦牧双形态PV公布",
        "type": 1,
        "type_title": "预告",
        "stat": {
            "coin": 1506,
            "dm": 166,
            "favorite": 540,
            "like": 4729,
            "reply": 468,
            "share": 190,
            "view": 1360123
        }
    },
    {
        "id": 2375218,
        "long_title": "不断更年番，正在热播！",
        "share_url": "https://www.bilibili.com/bangumi/play/ep2375218",
        "title": "PV",
        "type": 1,
        "type_title": "预告",
        "stat": {
            "coin": 3684,
            "dm": 150,
            "favorite": 1357,
            "like": 10055,
            "reply": 424,
            "share": 206,
            "view": 4283743
        }
    },
    {
        "id": 2307674,
        "long_title": "主创们私下竟然......",
        "share_url": "https://www.bilibili.com/bangumi/play/ep2307674",
        "title": "大青牛突击探班玄机科技！",
        "type": 1,
        "type_title": "预告",
        "stat": {
            "coin": 2706,
            "dm": 477,
            "favorite": 1041,
            "like": 6465,
            "reply": 250,
            "share": 189,
            "view": 2332041
        }
    },
    {
        "id": 2303505,
        "long_title": "【牧神记动画】开播一周年 牧儿携友送福来~",
        "share_url": "https://www.bilibili.com/bangumi/play/ep2303505",
        "title": "祝贺牧神记开播一周年",
        "type": 1,
        "type_title": "预告",
        "stat": {
            "coin": 789,
            "dm": 53,
            "favorite": 217,
            "like": 1551,
            "reply": 68,
            "share": 33,
            "view": 640916
        }
    },
    {
        "id": 2302551,
        "long_title": "",
        "share_url": "https://www.bilibili.com/bangumi/play/ep2302551",
        "title": "一周年主创访谈",
        "type": 1,
        "type_title": "预告",
        "stat": {
            "coin": 1516,
            "dm": 336,
            "favorite": 425,
            "like": 3638,
            "reply": 353,
            "share": 88,
            "view": 595659
        }
    },
    {
        "id": 2325305,
        "long_title": "牧神记动画一周年 娱乐主播阿饼倾情献唱动画主题曲《式微》",
        "share_url": "https://www.bilibili.com/bangumi/play/ep2325305",
        "title": "【实力翻唱】",
        "type": 1,
        "type_title": "预告",
        "stat": {
            "coin": 280,
            "dm": 18,
            "favorite": 110,
            "like": 2094,
            "reply": 30,
            "share": 27,
            "view": 375511
        }
    },
    {
        "id": 2319911,
        "long_title": "和秦牧一起陪伴爷爷奶奶",
        "share_url": "https://www.bilibili.com/bangumi/play/ep2319911",
        "title": "【公益】",
        "type": 1,
        "type_title": "预告",
        "stat": {
            "coin": 310,
            "dm": 13,
            "favorite": 125,
            "like": 2974,
            "reply": 21,
            "share": 11,
            "view": 299887
        }
    },
    {
        "id": 2289528,
        "long_title": "",
        "share_url": "https://www.bilibili.com/bangumi/play/ep2289528",
        "title": "花絮3：一镜到底带你看遍黄金宫！",
        "type": 1,
        "type_title": "预告",
        "stat": {
            "coin": 621,
            "dm": 56,
            "favorite": 198,
            "like": 2555,
            "reply": 103,
            "share": 33,
            "view": 651327
        }
    },
    {
        "id": 2289468,
        "long_title": "",
        "share_url": "https://www.bilibili.com/bangumi/play/ep2289468",
        "title": "花絮2：黄金宫原画揭秘！细节满满",
        "type": 1,
        "type_title": "预告",
        "stat": {
            "coin": 421,
            "dm": 13,
            "favorite": 117,
            "like": 2089,
            "reply": 78,
            "share": 24,
            "view": 376901
        }
    },
    {
        "id": 2285823,
        "long_title": "",
        "share_url": "https://www.bilibili.com/bangumi/play/ep2285823",
        "title": "花絮1：带你光顾秦牧的房间！",
        "type": 1,
        "type_title": "预告",
        "stat": {
            "coin": 378,
            "dm": 38,
            "favorite": 168,
            "like": 3057,
            "reply": 93,
            "share": 16,
            "view": 370507
        }
    },
    {
        "id": 2301846,
        "long_title": "暨大墟年会现场回顾",
        "share_url": "https://www.bilibili.com/bangumi/play/ep2301846",
        "title": "【牧神记动画】一周年庆典",
        "type": 1,
        "type_title": "预告",
        "stat": {
            "coin": 125,
            "dm": 10,
            "favorite": 41,
            "like": 285,
            "reply": 32,
            "share": 16,
            "view": 237992
        }
    },
    {
        "id": 2274133,
        "long_title": "黄霄雲为牧神记动画倾情打call",
        "share_url": "https://www.bilibili.com/bangumi/play/ep2274133",
        "title": "黄霄雲祝福视频",
        "type": 1,
        "type_title": "预告",
        "stat": {
            "coin": 297,
            "dm": 26,
            "favorite": 100,
            "like": 2273,
            "reply": 122,
            "share": 45,
            "view": 320650
        }
    },
    {
        "id": 2178878,
        "long_title": "",
        "share_url": "https://www.bilibili.com/bangumi/play/ep2178878",
        "title": "黄金宫篇PV",
        "type": 1,
        "type_title": "预告",
        "stat": {
            "coin": 1941,
            "dm": 182,
            "favorite": 714,
            "like": 5141,
            "reply": 299,
            "share": 151,
            "view": 2575023
        }
    },
    {
        "id": 2051707,
        "long_title": "吴垚滔现场演绎主题曲《天外的天》",
        "share_url": "https://www.bilibili.com/bangumi/play/ep2051707",
        "title": "【独家】豫园×牧神记动画",
        "type": 1,
        "type_title": "预告",
        "stat": {
            "coin": 2422,
            "dm": 475,
            "favorite": 1364,
            "like": 6466,
            "reply": 330,
            "share": 149,
            "view": 4246146
        }
    },
    {
        "id": 1881307,
        "long_title": "",
        "share_url": "https://www.bilibili.com/bangumi/play/ep1881307",
        "title": "灵毓秀宫装PV",
        "type": 1,
        "type_title": "预告",
        "stat": {
            "coin": 2687,
            "dm": 256,
            "favorite": 1500,
            "like": 6716,
            "reply": 305,
            "share": 248,
            "view": 3675706
        }
    },
    {
        "id": 1836776,
        "long_title": "",
        "share_url": "https://www.bilibili.com/bangumi/play/ep1836776",
        "title": "太学院篇PV",
        "type": 1,
        "type_title": "预告",
        "stat": {
            "coin": 1688,
            "dm": 169,
            "favorite": 742,
            "like": 4340,
            "reply": 259,
            "share": 125,
            "view": 1902792
        }
    },
    {
        "id": 1736860,
        "long_title": "",
        "share_url": "https://www.bilibili.com/bangumi/play/ep1736860",
        "title": "秦牧新造型PV",
        "type": 1,
        "type_title": "预告",
        "stat": {
            "coin": 2010,
            "dm": 162,
            "favorite": 795,
            "like": 4826,
            "reply": 290,
            "share": 130,
            "view": 2718974
        }
    },
    {
        "id": 1585302,
        "long_title": "",
        "share_url": "https://www.bilibili.com/bangumi/play/ep1585302",
        "title": "年番全新PV",
        "type": 1,
        "type_title": "预告",
        "stat": {
            "coin": 2238,
            "dm": 223,
            "favorite": 569,
            "like": 5813,
            "reply": 577,
            "share": 295,
            "view": 1435936
        }
    },
    {
        "id": 1466323,
        "long_title": "",
        "share_url": "https://www.bilibili.com/bangumi/play/ep1466323",
        "title": "灵毓秀角色pv",
        "type": 1,
        "type_title": "预告",
        "stat": {
            "coin": 5272,
            "dm": 400,
            "favorite": 2149,
            "like": 9383,
            "reply": 599,
            "share": 361,
            "view": 5702407
        }
    },
    {
        "id": 1451451,
        "long_title": "",
        "share_url": "https://www.bilibili.com/bangumi/play/ep1451451",
        "title": "少年版秦牧角色PV",
        "type": 1,
        "type_title": "预告",
        "stat": {
            "coin": 2495,
            "dm": 208,
            "favorite": 1061,
            "like": 5311,
            "reply": 446,
            "share": 262,
            "view": 2683464
        }
    },
    {
        "id": 1225107,
        "long_title": "",
        "share_url": "https://www.bilibili.com/bangumi/play/ep1225107",
        "title": "苏绣纪录花絮特辑上线！",
        "type": 1,
        "type_title": "预告",
        "stat": {
            "coin": 4436,
            "dm": 483,
            "favorite": 1684,
            "like": 8212,
            "reply": 282,
            "share": 382,
            "view": 3746289
        }
    },
    {
        "id": 1214624,
        "long_title": "与其跪神乞怜，不如站着，做自己的神",
        "share_url": "https://www.bilibili.com/bangumi/play/ep1214624",
        "title": "年番PV",
        "type": 1,
        "type_title": "预告",
        "stat": {
            "coin": 3900,
            "dm": 315,
            "favorite": 1324,
            "like": 7236,
            "reply": 578,
            "share": 403,
            "view": 2647707
        }
    },
    {
        "id": 1112145,
        "long_title": "",
        "share_url": "https://www.bilibili.com/bangumi/play/ep1112145",
        "title": "开播PV",
        "type": 1,
        "type_title": "预告",
        "stat": {
            "coin": 3443,
            "dm": 378,
            "favorite": 1491,
            "like": 5905,
            "reply": 644,
            "share": 624,
            "view": 2738352
        }
    },
    {
        "id": 1112144,
        "long_title": "",
        "share_url": "https://www.bilibili.com/bangumi/play/ep1112144",
        "title": "秦牧角色PV",
        "type": 1,
        "type_title": "预告",
        "stat": {
            "coin": 1083,
            "dm": 214,
            "favorite": 416,
            "like": 2670,
            "reply": 355,
            "share": 168,
            "view": 1369348
        }
    },
    {
        "id": 1112143,
        "long_title": "",
        "share_url": "https://www.bilibili.com/bangumi/play/ep1112143",
        "title": "残老村九老群像PV",
        "type": 1,
        "type_title": "预告",
        "stat": {
            "coin": 1074,
            "dm": 189,
            "favorite": 521,
            "like": 2859,
            "reply": 330,
            "share": 238,
            "view": 1220050
        }
    },
    {
        "id": 1112142,
        "long_title": "",
        "share_url": "https://www.bilibili.com/bangumi/play/ep1112142",
        "title": "司幼幽角色PV",
        "type": 1,
        "type_title": "预告",
        "stat": {
            "coin": 845,
            "dm": 94,
            "favorite": 315,
            "like": 2399,
            "reply": 241,
            "share": 172,
            "view": 1125425
        }
    },
    {
        "id": 838379,
        "long_title": "",
        "share_url": "https://www.bilibili.com/bangumi/play/ep838379",
        "title": "场景PV公开！",
        "type": 1,
        "type_title": "预告",
        "stat": {
            "coin": 1430,
            "dm": 342,
            "favorite": 744,
            "like": 3637,
            "reply": 513,
            "share": 477,
            "view": 1232644
        }
    },
    {
        "id": 1112806,
        "long_title": "",
        "share_url": "https://www.bilibili.com/bangumi/play/ep1112806",
        "title": "陈楚生为牧神记开播倾情打call",
        "type": 1,
        "type_title": "预告",
        "stat": {
            "coin": 1064,
            "dm": 154,
            "favorite": 483,
            "like": 2422,
            "reply": 147,
            "share": 106,
            "view": 1241105
        }
    },
    {
        "id": 836715,
        "long_title": "放牛娃的传奇人生即将开始",
        "share_url": "https://www.bilibili.com/bangumi/play/ep836715",
        "title": "牧神记定档10月27日！",
        "type": 1,
        "type_title": "预告",
        "stat": {
            "coin": 2012,
            "dm": 706,
            "favorite": 1216,
            "like": 5902,
            "reply": 1374,
            "share": 1382,
            "view": 1626854
        }
    },
    {
        "id": 775978,
        "long_title": "放牧诸神，为芸芸众生而战！",
        "share_url": "https://www.bilibili.com/bangumi/play/ep775978",
        "title": "PV",
        "type": 1,
        "type_title": "预告",
        "stat": {
            "coin": 5265,
            "dm": 1760,
            "favorite": 3492,
            "like": 20806,
            "reply": 4562,
            "share": 3260,
            "view": 2445010
        }
    },
    {
        "id": 1113958,
        "long_title": "",
        "share_url": "https://www.bilibili.com/bangumi/play/ep1113958",
        "title": "片尾曲《不息》乐队版MV",
        "type": 1,
        "type_title": "预告",
        "stat": {
            "coin": 2841,
            "dm": 258,
            "favorite": 1639,
            "like": 4662,
            "reply": 277,
            "share": 188,
            "view": 2182514
        }
    },
    {
        "id": 1112196,
        "long_title": "",
        "share_url": "https://www.bilibili.com/bangumi/play/ep1112196",
        "title": "第2集预告",
        "type": 1,
        "type_title": "预告",
        "stat": {
            "coin": 653,
            "dm": 70,
            "favorite": 259,
            "like": 1584,
            "reply": 56,
            "share": 39,
            "view": 1038002
        }
    },
    {
        "id": 1112279,
        "long_title": "",
        "share_url": "https://www.bilibili.com/bangumi/play/ep1112279",
        "title": "第3集预告",
        "type": 1,
        "type_title": "预告",
        "stat": {
            "coin": 4552,
            "dm": 494,
            "favorite": 1308,
            "like": 7629,
            "reply": 670,
            "share": 155,
            "view": 2053648
        }
    },
    {
        "id": 1112280,
        "long_title": "",
        "share_url": "https://www.bilibili.com/bangumi/play/ep1112280",
        "title": "第4集预告",
        "type": 1,
        "type_title": "预告",
        "stat": {
            "coin": 2848,
            "dm": 274,
            "favorite": 839,
            "like": 5721,
            "reply": 300,
            "share": 110,
            "view": 2128082
        }
    },
    {
        "id": 1112281,
        "long_title": "",
        "share_url": "https://www.bilibili.com/bangumi/play/ep1112281",
        "title": "第5集预告",
        "type": 1,
        "type_title": "预告",
        "stat": {
            "coin": 3505,
            "dm": 256,
            "favorite": 936,
            "like": 6537,
            "reply": 366,
            "share": 98,
            "view": 2367958
        }
    },
    {
        "id": 1112282,
        "long_title": "",
        "share_url": "https://www.bilibili.com/bangumi/play/ep1112282",
        "title": "第6集预告",
        "type": 1,
        "type_title": "预告",
        "stat": {
            "coin": 3563,
            "dm": 172,
            "favorite": 904,
            "like": 6783,
            "reply": 399,
            "share": 136,
            "view": 2322275
        }
    },
    {
        "id": 1112283,
        "long_title": "",
        "share_url": "https://www.bilibili.com/bangumi/play/ep1112283",
        "title": "第7集预告",
        "type": 1,
        "type_title": "预告",
        "stat": {
            "coin": 3613,
            "dm": 245,
            "favorite": 837,
            "like": 6653,
            "reply": 269,
            "share": 84,
            "view": 2311630
        }
    },
    {
        "id": 1112284,
        "long_title": "",
        "share_url": "https://www.bilibili.com/bangumi/play/ep1112284",
        "title": "第8集预告",
        "type": 1,
        "type_title": "预告",
        "stat": {
            "coin": 4613,
            "dm": 215,
            "favorite": 988,
            "like": 7432,
            "reply": 267,
            "share": 127,
            "view": 2399727
        }
    },
    {
        "id": 1112285,
        "long_title": "",
        "share_url": "https://www.bilibili.com/bangumi/play/ep1112285",
        "title": "第9集预告",
        "type": 1,
        "type_title": "预告",
        "stat": {
            "coin": 3600,
            "dm": 152,
            "favorite": 787,
            "like": 6318,
            "reply": 292,
            "share": 90,
            "view": 2154370
        }
    },
    {
        "id": 1112286,
        "long_title": "",
        "share_url": "https://www.bilibili.com/bangumi/play/ep1112286",
        "title": "第10集预告",
        "type": 1,
        "type_title": "预告",
        "stat": {
            "coin": 4258,
            "dm": 110,
            "favorite": 883,
            "like": 7315,
            "reply": 341,
            "share": 104,
            "view": 2245072
        }
    },
    {
        "id": 1112287,
        "long_title": "",
        "share_url": "https://www.bilibili.com/bangumi/play/ep1112287",
        "title": "第11集预告",
        "type": 1,
        "type_title": "预告",
        "stat": {
            "coin": 3192,
            "dm": 158,
            "favorite": 828,
            "like": 6443,
            "reply": 313,
            "share": 104,
            "view": 2445334
        }
    },
    {
        "id": 1112288,
        "long_title": "",
        "share_url": "https://www.bilibili.com/bangumi/play/ep1112288",
        "title": "第12集预告",
        "type": 1,
        "type_title": "预告",
        "stat": {
            "coin": 3578,
            "dm": 233,
            "favorite": 710,
            "like": 6750,
            "reply": 230,
            "share": 115,
            "view": 2221800
        }
    },
    {
        "id": 1112289,
        "long_title": "",
        "share_url": "https://www.bilibili.com/bangumi/play/ep1112289",
        "title": "第13集预告",
        "type": 1,
        "type_title": "预告",
        "stat": {
            "coin": 2600,
            "dm": 109,
            "favorite": 682,
            "like": 5723,
            "reply": 227,
            "share": 77,
            "view": 2195033
        }
    },
    {
        "id": 1112290,
        "long_title": "",
        "share_url": "https://www.bilibili.com/bangumi/play/ep1112290",
        "title": "第14集预告",
        "type": 1,
        "type_title": "预告",
        "stat": {
            "coin": 4856,
            "dm": 223,
            "favorite": 2573,
            "like": 9153,
            "reply": 475,
            "share": 218,
            "view": 5995157
        }
    },
    {
        "id": 1112291,
        "long_title": "",
        "share_url": "https://www.bilibili.com/bangumi/play/ep1112291",
        "title": "第15集预告",
        "type": 1,
        "type_title": "预告",
        "stat": {
            "coin": 3397,
            "dm": 166,
            "favorite": 1198,
            "like": 6911,
            "reply": 399,
            "share": 107,
            "view": 3729042
        }
    },
    {
        "id": 1112292,
        "long_title": "",
        "share_url": "https://www.bilibili.com/bangumi/play/ep1112292",
        "title": "第16集预告",
        "type": 1,
        "type_title": "预告",
        "stat": {
            "coin": 3620,
            "dm": 127,
            "favorite": 930,
            "like": 7290,
            "reply": 348,
            "share": 103,
            "view": 3130418
        }
    },
    {
        "id": 1112293,
        "long_title": "",
        "share_url": "https://www.bilibili.com/bangumi/play/ep1112293",
        "title": "第17集预告",
        "type": 1,
        "type_title": "预告",
        "stat": {
            "coin": 3808,
            "dm": 202,
            "favorite": 977,
            "like": 7549,
            "reply": 376,
            "share": 115,
            "view": 3066831
        }
    },
    {
        "id": 1112294,
        "long_title": "",
        "share_url": "https://www.bilibili.com/bangumi/play/ep1112294",
        "title": "第18集预告",
        "type": 1,
        "type_title": "预告",
        "stat": {
            "coin": 4326,
            "dm": 245,
            "favorite": 1032,
            "like": 8589,
            "reply": 633,
            "share": 279,
            "view": 3062318
        }
    },
    {
        "id": 1112295,
        "long_title": "",
        "share_url": "https://www.bilibili.com/bangumi/play/ep1112295",
        "title": "第19集预告",
        "type": 1,
        "type_title": "预告",
        "stat": {
            "coin": 6101,
            "dm": 192,
            "favorite": 1626,
            "like": 11007,
            "reply": 652,
            "share": 242,
            "view": 3981922
        }
    },
    {
        "id": 1112296,
        "long_title": "",
        "share_url": "https://www.bilibili.com/bangumi/play/ep1112296",
        "title": "第20集预告",
        "type": 1,
        "type_title": "预告",
        "stat": {
            "coin": 4520,
            "dm": 251,
            "favorite": 1287,
            "like": 8976,
            "reply": 559,
            "share": 355,
            "view": 3474343
        }
    },
    {
        "id": 1112297,
        "long_title": "",
        "share_url": "https://www.bilibili.com/bangumi/play/ep1112297",
        "title": "第21集预告",
        "type": 1,
        "type_title": "预告",
        "stat": {
            "coin": 4436,
            "dm": 228,
            "favorite": 1048,
            "like": 8970,
            "reply": 580,
            "share": 223,
            "view": 3508059
        }
    },
    {
        "id": 1112298,
        "long_title": "",
        "share_url": "https://www.bilibili.com/bangumi/play/ep1112298",
        "title": "第22集预告",
        "type": 1,
        "type_title": "预告",
        "stat": {
            "coin": 4912,
            "dm": 399,
            "favorite": 1146,
            "like": 9357,
            "reply": 620,
            "share": 136,
            "view": 3386375
        }
    },
    {
        "id": 1112299,
        "long_title": "",
        "share_url": "https://www.bilibili.com/bangumi/play/ep1112299",
        "title": "第23集预告",
        "type": 1,
        "type_title": "预告",
        "stat": {
            "coin": 4703,
            "dm": 209,
            "favorite": 968,
            "like": 9182,
            "reply": 722,
            "share": 234,
            "view": 3089428
        }
    },
    {
        "id": 1112300,
        "long_title": "",
        "share_url": "https://www.bilibili.com/bangumi/play/ep1112300",
        "title": "第24集预告",
        "type": 1,
        "type_title": "预告",
        "stat": {
            "coin": 5617,
            "dm": 450,
            "favorite": 970,
            "like": 10093,
            "reply": 1048,
            "share": 201,
            "view": 3184097
        }
    },
    {
        "id": 1112301,
        "long_title": "年番定档4月20日",
        "share_url": "https://www.bilibili.com/bangumi/play/ep1112301",
        "title": "第25集预告",
        "type": 1,
        "type_title": "预告",
        "stat": {
            "coin": 10215,
            "dm": 502,
            "favorite": 1800,
            "like": 15236,
            "reply": 953,
            "share": 454,
            "view": 3620789
        }
    },
    {
        "id": 1112302,
        "long_title": "",
        "share_url": "https://www.bilibili.com/bangumi/play/ep1112302",
        "title": "第26集预告",
        "type": 1,
        "type_title": "预告",
        "stat": {
            "coin": 4168,
            "dm": 221,
            "favorite": 747,
            "like": 8493,
            "reply": 458,
            "share": 116,
            "view": 2671671
        }
    },
    {
        "id": 1529070,
        "long_title": "",
        "share_url": "https://www.bilibili.com/bangumi/play/ep1529070",
        "title": "第27集预告",
        "type": 1,
        "type_title": "预告",
        "stat": {
            "coin": 4923,
            "dm": 270,
            "favorite": 814,
            "like": 9474,
            "reply": 536,
            "share": 113,
            "view": 2869683
        }
    },
    {
        "id": 1529071,
        "long_title": "",
        "share_url": "https://www.bilibili.com/bangumi/play/ep1529071",
        "title": "第28集预告",
        "type": 1,
        "type_title": "预告",
        "stat": {
            "coin": 3557,
            "dm": 188,
            "favorite": 612,
            "like": 7568,
            "reply": 460,
            "share": 111,
            "view": 2599368
        }
    },
    {
        "id": 1529072,
        "long_title": "",
        "share_url": "https://www.bilibili.com/bangumi/play/ep1529072",
        "title": "第29集预告",
        "type": 1,
        "type_title": "预告",
        "stat": {
            "coin": 3107,
            "dm": 150,
            "favorite": 561,
            "like": 6802,
            "reply": 313,
            "share": 79,
            "view": 2330160
        }
    },
    {
        "id": 1529073,
        "long_title": "",
        "share_url": "https://www.bilibili.com/bangumi/play/ep1529073",
        "title": "第30集预告",
        "type": 1,
        "type_title": "预告",
        "stat": {
            "coin": 2868,
            "dm": 166,
            "favorite": 552,
            "like": 6740,
            "reply": 393,
            "share": 86,
            "view": 2357307
        }
    },
    {
        "id": 1529074,
        "long_title": "",
        "share_url": "https://www.bilibili.com/bangumi/play/ep1529074",
        "title": "第31集预告",
        "type": 1,
        "type_title": "预告",
        "stat": {
            "coin": 2565,
            "dm": 147,
            "favorite": 447,
            "like": 6036,
            "reply": 296,
            "share": 63,
            "view": 2166290
        }
    },
    {
        "id": 1529075,
        "long_title": "",
        "share_url": "https://www.bilibili.com/bangumi/play/ep1529075",
        "title": "第32集预告",
        "type": 1,
        "type_title": "预告",
        "stat": {
            "coin": 2720,
            "dm": 185,
            "favorite": 567,
            "like": 6408,
            "reply": 340,
            "share": 67,
            "view": 2084361
        }
    },
    {
        "id": 1529076,
        "long_title": "",
        "share_url": "https://www.bilibili.com/bangumi/play/ep1529076",
        "title": "第33集预告",
        "type": 1,
        "type_title": "预告",
        "stat": {
            "coin": 2948,
            "dm": 174,
            "favorite": 565,
            "like": 6604,
            "reply": 318,
            "share": 77,
            "view": 2230701
        }
    },
    {
        "id": 1529077,
        "long_title": "",
        "share_url": "https://www.bilibili.com/bangumi/play/ep1529077",
        "title": "第34集预告",
        "type": 1,
        "type_title": "预告",
        "stat": {
            "coin": 2573,
            "dm": 160,
            "favorite": 486,
            "like": 5907,
            "reply": 248,
            "share": 63,
            "view": 1927575
        }
    },
    {
        "id": 1529078,
        "long_title": "",
        "share_url": "https://www.bilibili.com/bangumi/play/ep1529078",
        "title": "第35集预告",
        "type": 1,
        "type_title": "预告",
        "stat": {
            "coin": 2715,
            "dm": 179,
            "favorite": 511,
            "like": 6270,
            "reply": 415,
            "share": 62,
            "view": 2175540
        }
    },
    {
        "id": 1529079,
        "long_title": "",
        "share_url": "https://www.bilibili.com/bangumi/play/ep1529079",
        "title": "第36集预告",
        "type": 1,
        "type_title": "预告",
        "stat": {
            "coin": 2950,
            "dm": 232,
            "favorite": 533,
            "like": 6616,
            "reply": 383,
            "share": 70,
            "view": 2186294
        }
    },
    {
        "id": 1529080,
        "long_title": "",
        "share_url": "https://www.bilibili.com/bangumi/play/ep1529080",
        "title": "第37集预告",
        "type": 1,
        "type_title": "预告",
        "stat": {
            "coin": 3154,
            "dm": 164,
            "favorite": 555,
            "like": 6468,
            "reply": 250,
            "share": 73,
            "view": 2029071
        }
    },
    {
        "id": 1529081,
        "long_title": "",
        "share_url": "https://www.bilibili.com/bangumi/play/ep1529081",
        "title": "第38集预告",
        "type": 1,
        "type_title": "预告",
        "stat": {
            "coin": 3594,
            "dm": 269,
            "favorite": 683,
            "like": 7077,
            "reply": 545,
            "share": 62,
            "view": 2014678
        }
    },
    {
        "id": 1529082,
        "long_title": "",
        "share_url": "https://www.bilibili.com/bangumi/play/ep1529082",
        "title": "第39集预告",
        "type": 1,
        "type_title": "预告",
        "stat": {
            "coin": 3528,
            "dm": 208,
            "favorite": 649,
            "like": 7286,
            "reply": 316,
            "share": 65,
            "view": 2283437
        }
    },
    {
        "id": 1529083,
        "long_title": "",
        "share_url": "https://www.bilibili.com/bangumi/play/ep1529083",
        "title": "第40集预告",
        "type": 1,
        "type_title": "预告",
        "stat": {
            "coin": 4622,
            "dm": 382,
            "favorite": 902,
            "like": 9824,
            "reply": 608,
            "share": 85,
            "view": 3106264
        }
    },
    {
        "id": 1529084,
        "long_title": "",
        "share_url": "https://www.bilibili.com/bangumi/play/ep1529084",
        "title": "第41集预告",
        "type": 1,
        "type_title": "预告",
        "stat": {
            "coin": 3813,
            "dm": 447,
            "favorite": 805,
            "like": 8320,
            "reply": 631,
            "share": 78,
            "view": 2587490
        }
    },
    {
        "id": 1529085,
        "long_title": "",
        "share_url": "https://www.bilibili.com/bangumi/play/ep1529085",
        "title": "第42集预告",
        "type": 1,
        "type_title": "预告",
        "stat": {
            "coin": 3850,
            "dm": 522,
            "favorite": 771,
            "like": 8475,
            "reply": 600,
            "share": 62,
            "view": 2929780
        }
    },
    {
        "id": 1529086,
        "long_title": "",
        "share_url": "https://www.bilibili.com/bangumi/play/ep1529086",
        "title": "第43集预告",
        "type": 1,
        "type_title": "预告",
        "stat": {
            "coin": 3542,
            "dm": 351,
            "favorite": 715,
            "like": 7741,
            "reply": 329,
            "share": 68,
            "view": 2538883
        }
    },
    {
        "id": 1529087,
        "long_title": "",
        "share_url": "https://www.bilibili.com/bangumi/play/ep1529087",
        "title": "第44集预告",
        "type": 1,
        "type_title": "预告",
        "stat": {
            "coin": 3696,
            "dm": 476,
            "favorite": 763,
            "like": 8361,
            "reply": 536,
            "share": 69,
            "view": 2780609
        }
    },
    {
        "id": 1529088,
        "long_title": "",
        "share_url": "https://www.bilibili.com/bangumi/play/ep1529088",
        "title": "第45集预告",
        "type": 1,
        "type_title": "预告",
        "stat": {
            "coin": 4348,
            "dm": 465,
            "favorite": 1022,
            "like": 9612,
            "reply": 719,
            "share": 80,
            "view": 3474145
        }
    },
    {
        "id": 1529089,
        "long_title": "",
        "share_url": "https://www.bilibili.com/bangumi/play/ep1529089",
        "title": "第46集预告",
        "type": 1,
        "type_title": "预告",
        "stat": {
            "coin": 4400,
            "dm": 541,
            "favorite": 981,
            "like": 9844,
            "reply": 987,
            "share": 75,
            "view": 3576883
        }
    },
    {
        "id": 1529090,
        "long_title": "",
        "share_url": "https://www.bilibili.com/bangumi/play/ep1529090",
        "title": "第47集预告",
        "type": 1,
        "type_title": "预告",
        "stat": {
            "coin": 4060,
            "dm": 396,
            "favorite": 749,
            "like": 8517,
            "reply": 907,
            "share": 82,
            "view": 2727309
        }
    },
    {
        "id": 1529091,
        "long_title": "",
        "share_url": "https://www.bilibili.com/bangumi/play/ep1529091",
        "title": "第48集预告",
        "type": 1,
        "type_title": "预告",
        "stat": {
            "coin": 3964,
            "dm": 284,
            "favorite": 790,
            "like": 8970,
            "reply": 705,
            "share": 70,
            "view": 3342794
        }
    },
    {
        "id": 1529092,
        "long_title": "",
        "share_url": "https://www.bilibili.com/bangumi/play/ep1529092",
        "title": "第49集预告",
        "type": 1,
        "type_title": "预告",
        "stat": {
            "coin": 3648,
            "dm": 258,
            "favorite": 704,
            "like": 8063,
            "reply": 495,
            "share": 86,
            "view": 2668239
        }
    },
    {
        "id": 1529093,
        "long_title": "",
        "share_url": "https://www.bilibili.com/bangumi/play/ep1529093",
        "title": "第50集预告",
        "type": 1,
        "type_title": "预告",
        "stat": {
            "coin": 4541,
            "dm": 401,
            "favorite": 825,
            "like": 8537,
            "reply": 603,
            "share": 70,
            "view": 2154551
        }
    },
    {
        "id": 1529094,
        "long_title": "",
        "share_url": "https://www.bilibili.com/bangumi/play/ep1529094",
        "title": "第51集预告",
        "type": 1,
        "type_title": "预告",
        "stat": {
            "coin": 3919,
            "dm": 255,
            "favorite": 768,
            "like": 8630,
            "reply": 557,
            "share": 79,
            "view": 2622726
        }
    },
    {
        "id": 1529095,
        "long_title": "",
        "share_url": "https://www.bilibili.com/bangumi/play/ep1529095",
        "title": "第52集预告",
        "type": 1,
        "type_title": "预告",
        "stat": {
            "coin": 4585,
            "dm": 541,
            "favorite": 909,
            "like": 9420,
            "reply": 840,
            "share": 83,
            "view": 3261384
        }
    },
    {
        "id": 1529096,
        "long_title": "",
        "share_url": "https://www.bilibili.com/bangumi/play/ep1529096",
        "title": "第53集预告",
        "type": 1,
        "type_title": "预告",
        "stat": {
            "coin": 4393,
            "dm": 384,
            "favorite": 783,
            "like": 9274,
            "reply": 689,
            "share": 89,
            "view": 3038968
        }
    },
    {
        "id": 1529097,
        "long_title": "",
        "share_url": "https://www.bilibili.com/bangumi/play/ep1529097",
        "title": "第54集预告",
        "type": 1,
        "type_title": "预告",
        "stat": {
            "coin": 4530,
            "dm": 428,
            "favorite": 759,
            "like": 10049,
            "reply": 712,
            "share": 68,
            "view": 3241636
        }
    },
    {
        "id": 1529098,
        "long_title": "",
        "share_url": "https://www.bilibili.com/bangumi/play/ep1529098",
        "title": "第55集预告",
        "type": 1,
        "type_title": "预告",
        "stat": {
            "coin": 5728,
            "dm": 285,
            "favorite": 999,
            "like": 9603,
            "reply": 601,
            "share": 69,
            "view": 2684674
        }
    },
    {
        "id": 1529099,
        "long_title": "",
        "share_url": "https://www.bilibili.com/bangumi/play/ep1529099",
        "title": "第56集预告",
        "type": 1,
        "type_title": "预告",
        "stat": {
            "coin": 5237,
            "dm": 289,
            "favorite": 819,
            "like": 9609,
            "reply": 498,
            "share": 85,
            "view": 2592269
        }
    },
    {
        "id": 1529100,
        "long_title": "",
        "share_url": "https://www.bilibili.com/bangumi/play/ep1529100",
        "title": "第57集预告",
        "type": 1,
        "type_title": "预告",
        "stat": {
            "coin": 5249,
            "dm": 253,
            "favorite": 848,
            "like": 9630,
            "reply": 816,
            "share": 72,
            "view": 2758290
        }
    },
    {
        "id": 1529101,
        "long_title": "",
        "share_url": "https://www.bilibili.com/bangumi/play/ep1529101",
        "title": "第58集预告",
        "type": 1,
        "type_title": "预告",
        "stat": {
            "coin": 4167,
            "dm": 251,
            "favorite": 718,
            "like": 8616,
            "reply": 377,
            "share": 83,
            "view": 2738498
        }
    },
    {
        "id": 1529102,
        "long_title": "",
        "share_url": "https://www.bilibili.com/bangumi/play/ep1529102",
        "title": "第59集预告",
        "type": 1,
        "type_title": "预告",
        "stat": {
            "coin": 5531,
            "dm": 257,
            "favorite": 770,
            "like": 9498,
            "reply": 464,
            "share": 60,
            "view": 2498842
        }
    },
    {
        "id": 1529103,
        "long_title": "",
        "share_url": "https://www.bilibili.com/bangumi/play/ep1529103",
        "title": "第60集预告",
        "type": 1,
        "type_title": "预告",
        "stat": {
            "coin": 3945,
            "dm": 251,
            "favorite": 654,
            "like": 8441,
            "reply": 468,
            "share": 69,
            "view": 2442528
        }
    },
    {
        "id": 1529104,
        "long_title": "",
        "share_url": "https://www.bilibili.com/bangumi/play/ep1529104",
        "title": "第61集预告",
        "type": 1,
        "type_title": "预告",
        "stat": {
            "coin": 4381,
            "dm": 239,
            "favorite": 742,
            "like": 8873,
            "reply": 356,
            "share": 78,
            "view": 2453972
        }
    },
    {
        "id": 1529105,
        "long_title": "",
        "share_url": "https://www.bilibili.com/bangumi/play/ep1529105",
        "title": "第62集预告",
        "type": 1,
        "type_title": "预告",
        "stat": {
            "coin": 3855,
            "dm": 256,
            "favorite": 674,
            "like": 8510,
            "reply": 533,
            "share": 64,
            "view": 2533830
        }
    },
    {
        "id": 1529106,
        "long_title": "",
        "share_url": "https://www.bilibili.com/bangumi/play/ep1529106",
        "title": "第63集预告",
        "type": 1,
        "type_title": "预告",
        "stat": {
            "coin": 4457,
            "dm": 264,
            "favorite": 679,
            "like": 9420,
            "reply": 806,
            "share": 69,
            "view": 2607993
        }
    },
    {
        "id": 1529107,
        "long_title": "",
        "share_url": "https://www.bilibili.com/bangumi/play/ep1529107",
        "title": "第64集预告",
        "type": 1,
        "type_title": "预告",
        "stat": {
            "coin": 5151,
            "dm": 1701,
            "favorite": 818,
            "like": 9804,
            "reply": 551,
            "share": 91,
            "view": 2316211
        }
    },
    {
        "id": 1529108,
        "long_title": "",
        "share_url": "https://www.bilibili.com/bangumi/play/ep1529108",
        "title": "第65集预告",
        "type": 1,
        "type_title": "预告",
        "stat": {
            "coin": 3779,
            "dm": 185,
            "favorite": 595,
            "like": 7815,
            "reply": 453,
            "share": 70,
            "view": 1970103
        }
    },
    {
        "id": 1529109,
        "long_title": "",
        "share_url": "https://www.bilibili.com/bangumi/play/ep1529109",
        "title": "第66集预告",
        "type": 1,
        "type_title": "预告",
        "stat": {
            "coin": 4876,
            "dm": 285,
            "favorite": 849,
            "like": 10315,
            "reply": 1242,
            "share": 98,
            "view": 3279802
        }
    },
    {
        "id": 1529110,
        "long_title": "",
        "share_url": "https://www.bilibili.com/bangumi/play/ep1529110",
        "title": "第67集预告",
        "type": 1,
        "type_title": "预告",
        "stat": {
            "coin": 5155,
            "dm": 274,
            "favorite": 865,
            "like": 10192,
            "reply": 1007,
            "share": 91,
            "view": 2775676
        }
    },
    {
        "id": 1529111,
        "long_title": "",
        "share_url": "https://www.bilibili.com/bangumi/play/ep1529111",
        "title": "第68集预告",
        "type": 1,
        "type_title": "预告",
        "stat": {
            "coin": 3731,
            "dm": 284,
            "favorite": 548,
            "like": 8126,
            "reply": 850,
            "share": 50,
            "view": 1622735
        }
    },
    {
        "id": 2265606,
        "long_title": "",
        "share_url": "https://www.bilibili.com/bangumi/play/ep2265606",
        "title": "【独家】牧神记全新片尾曲《式微》",
        "type": 2,
        "type_title": "特别花絮",
        "stat": {
            "coin": 3615,
            "dm": 322,
            "favorite": 1483,
            "like": 7861,
            "reply": 646,
            "share": 315,
            "view": 2784103
        }
    },
    {
        "id": 2291407,
        "long_title": "",
        "share_url": "https://www.bilibili.com/bangumi/play/ep2291407",
        "title": "牧神记片尾曲《式微》制作花絮公开",
        "type": 2,
        "type_title": "特别花絮",
        "stat": {
            "coin": 328,
            "dm": 51,
            "favorite": 138,
            "like": 994,
            "reply": 44,
            "share": 58,
            "view": 322517
        }
    },
    {
        "id": 2265602,
        "long_title": "",
        "share_url": "https://www.bilibili.com/bangumi/play/ep2265602",
        "title": "【独家】牧神记OP全新画面发布",
        "type": 2,
        "type_title": "特别花絮",
        "stat": {
            "coin": 1114,
            "dm": 152,
            "favorite": 485,
            "like": 3957,
            "reply": 383,
            "share": 120,
            "view": 510845
        }
    },
    {
        "id": 1587548,
        "long_title": "《天外的天》",
        "share_url": "https://www.bilibili.com/bangumi/play/ep1587548",
        "title": "年番新画面OP",
        "type": 2,
        "type_title": "特别花絮",
        "stat": {
            "coin": 3557,
            "dm": 245,
            "favorite": 1541,
            "like": 7530,
            "reply": 359,
            "share": 317,
            "view": 3713657
        }
    },
    {
        "id": 1587537,
        "long_title": "《不息》",
        "share_url": "https://www.bilibili.com/bangumi/play/ep1587537",
        "title": "年番新画面ED",
        "type": 2,
        "type_title": "特别花絮",
        "stat": {
            "coin": 1779,
            "dm": 237,
            "favorite": 810,
            "like": 4511,
            "reply": 355,
            "share": 168,
            "view": 1461391
        }
    },
    {
        "id": 1111885,
        "long_title": "陈楚生《天外的天》",
        "share_url": "https://www.bilibili.com/bangumi/play/ep1111885",
        "title": "牧神记OP",
        "type": 2,
        "type_title": "特别花絮",
        "stat": {
            "coin": 5581,
            "dm": 2138,
            "favorite": 3307,
            "like": 10739,
            "reply": 1252,
            "share": 1455,
            "view": 1529409
        }
    },
    {
        "id": 1113439,
        "long_title": "《不息》正式上线",
        "share_url": "https://www.bilibili.com/bangumi/play/ep1113439",
        "title": "牧神记ED",
        "type": 2,
        "type_title": "特别花絮",
        "stat": {
            "coin": 1359,
            "dm": 142,
            "favorite": 733,
            "like": 3243,
            "reply": 138,
            "share": 161,
            "view": 1269069
        }
    }
]