[
    {
        "id": 836727,
        "long_title": "天黑别出门",
        "share_url": "https://www.bilibili.com/bangumi/play/ep836727",
        "title": "1",
        "type": 0,
        "type_title": "正片",
        "stat": {
            "coin": 114902,
            "dm": 113547,
            "favorite": 142160,
            "like": 256404,
            "reply": 8565,
            "share": 26229,
            "view": 85840724
        }
    },
    {
        "id": 1112251,
        "long_title": "我是霸体",
        "share_url": "https://www.bilibili.com/bangumi/play/ep1112251",
        "title": "2",
        "type": 0,
        "type_title": "正片",
        "stat": {
            "coin": 51780,
            "dm": 44357,
            "favorite": 18227,
            "like": 90286,
            "reply": 2703,
            "share": 3590,
            "view": 23040631
        }
    },
    {
        "id": 1112253,
        "long_title": "小魔崽子",
        "share_url": "https://www.bilibili.com/bangumi/play/ep1112253",
        "title": "3",
        "type": 0,
        "type_title": "正片",
        "stat": {
            "coin": 42314,
            "dm": 23670,
            "favorite": 13687,
            "like": 76026,
            "reply": 1699,
            "share": 2278,
            "view": 21835824
        }
    },
    {
        "id": 1113172,
        "long_title": "黑暗将至",
        "share_url": "https://www.bilibili.com/bangumi/play/ep1113172",
        "title": "4",
        "type": 0,
        "type_title": "正片",
        "stat": {
            "coin": 41745,
            "dm": 22856,
            "favorite": 11941,
            "like": 70558,
            "reply": 1561,
            "share": 2178,
            "view": 20454714
        }
    },
    {
        "id": 1114406,
        "long_title": "红粉骷髅",
        "share_url": "https://www.bilibili.com/bangumi/play/ep1114406",
        "title": "5",
        "type": 0,
        "type_title": "正片",
        "stat": {
            "coin": 48655,
            "dm": 33279,
            "favorite": 11632,
            "like": 76260,
            "reply": 2244,
            "share": 2388,
            "view": 20423726
        }
    },
    {
        "id": 1114407,
        "long_title": "神魔共鸣",
        "share_url": "https://www.bilibili.com/bangumi/play/ep1114407",
        "title": "6",
        "type": 0,
        "type_title": "正片",
        "stat": {
            "coin": 121297,
            "dm": 28415,
            "favorite": 19832,
            "like": 129506,
            "reply": 1544,
            "share": 1959,
            "view": 20646477
        }
    },
    {
        "id": 1115673,
        "long_title": "三音破壁",
        "share_url": "https://www.bilibili.com/bangumi/play/ep1115673",
        "title": "7",
        "type": 0,
        "type_title": "正片",
        "stat": {
            "coin": 131779,
            "dm": 31455,
            "favorite": 25658,
            "like": 137964,
            "reply": 1703,
            "share": 1919,
            "view": 24960137
        }
    },
    {
        "id": 1115674,
        "long_title": "破心中神",
        "share_url": "https://www.bilibili.com/bangumi/play/ep1115674",
        "title": "8",
        "type": 0,
        "type_title": "正片",
        "stat": {
            "coin": 114265,
            "dm": 119045,
            "favorite": 23086,
            "like": 135259,
            "reply": 2113,
            "share": 1966,
            "view": 24469786
        }
    },
    {
        "id": 1115675,
        "long_title": "壁画寻古",
        "share_url": "https://www.bilibili.com/bangumi/play/ep1115675",
        "title": "9",
        "type": 0,
        "type_title": "正片",
        "stat": {
            "coin": 99763,
            "dm": 22046,
            "favorite": 17134,
            "like": 114583,
            "reply": 1822,
            "share": 1741,
            "view": 20892840
        }
    },
    {
        "id": 1115676,
        "long_title": "小骗子，大骗子",
        "share_url": "https://www.bilibili.com/bangumi/play/ep1115676",
        "title": "10",
        "type": 0,
        "type_title": "正片",
        "stat": {
            "coin": 92861,
            "dm": 87006,
            "favorite": 13952,
            "like": 101237,
            "reply": 1354,
            "share": 1439,
            "view": 19420950
        }
    },
    {
        "id": 1192425,
        "long_title": "漓江剑法",
        "share_url": "https://www.bilibili.com/bangumi/play/ep1192425",
        "title": "11",
        "type": 0,
        "type_title": "正片",
        "stat": {
            "coin": 92385,
            "dm": 43403,
            "favorite": 15962,
            "like": 105980,
            "reply": 1773,
            "share": 1766,
            "view": 20814347
        }
    },
    {
        "id": 1192426,
        "long_title": "魔印禅心",
        "share_url": "https://www.bilibili.com/bangumi/play/ep1192426",
        "title": "12",
        "type": 0,
        "type_title": "正片",
        "stat": {
            "coin": 52733,
            "dm": 25169,
            "favorite": 11666,
            "like": 77674,
            "reply": 1368,
            "share": 1562,
            "view": 21626734
        }
    },
    {
        "id": 1192427,
        "long_title": "深夜魅影",
        "share_url": "https://www.bilibili.com/bangumi/play/ep1192427",
        "title": "13",
        "type": 0,
        "type_title": "正片",
        "stat": {
            "coin": 70699,
            "dm": 18724,
            "favorite": 16326,
            "like": 96400,
            "reply": 1688,
            "share": 1608,
            "view": 25240402
        }
    },
    {
        "id": 1192428,
        "long_title": "涌江龙宫",
        "share_url": "https://www.bilibili.com/bangumi/play/ep1192428",
        "title": "14",
        "type": 0,
        "type_title": "正片",
        "stat": {
            "coin": 66163,
            "dm": 61790,
            "favorite": 12618,
            "like": 83659,
            "reply": 1674,
            "share": 1839,
            "view": 20431740
        }
    },
    {
        "id": 1192429,
        "long_title": "太子少保",
        "share_url": "https://www.bilibili.com/bangumi/play/ep1192429",
        "title": "15",
        "type": 0,
        "type_title": "正片",
        "stat": {
            "coin": 55360,
            "dm": 23389,
            "favorite": 9829,
            "like": 70893,
            "reply": 1530,
            "share": 1147,
            "view": 14791764
        }
    },
    {
        "id": 1192430,
        "long_title": "三百六十堂",
        "share_url": "https://www.bilibili.com/bangumi/play/ep1192430",
        "title": "16",
        "type": 0,
        "type_title": "正片",
        "stat": {
            "coin": 55002,
            "dm": 22997,
            "favorite": 9925,
            "like": 70075,
            "reply": 1719,
            "share": 1161,
            "view": 14991817
        }
    },
    {
        "id": 1192431,
        "long_title": "少教主",
        "share_url": "https://www.bilibili.com/bangumi/play/ep1192431",
        "title": "17",
        "type": 0,
        "type_title": "正片",
        "stat": {
            "coin": 59171,
            "dm": 34384,
            "favorite": 12926,
            "like": 78408,
            "reply": 2462,
            "share": 1523,
            "view": 17073658
        }
    },
    {
        "id": 1192432,
        "long_title": "冰潮",
        "share_url": "https://www.bilibili.com/bangumi/play/ep1192432",
        "title": "18",
        "type": 0,
        "type_title": "正片",
        "stat": {
            "coin": 74542,
            "dm": 23718,
            "favorite": 16681,
            "like": 93884,
            "reply": 4081,
            "share": 1892,
            "view": 19129282
        }
    },
    {
        "id": 1192433,
        "long_title": "残老挑江山",
        "share_url": "https://www.bilibili.com/bangumi/play/ep1192433",
        "title": "19",
        "type": 0,
        "type_title": "正片",
        "stat": {
            "coin": 60534,
            "dm": 22143,
            "favorite": 10169,
            "like": 73169,
            "reply": 2288,
            "share": 1451,
            "view": 14715880
        }
    },
    {
        "id": 1192445,
        "long_title": "不夜城",
        "share_url": "https://www.bilibili.com/bangumi/play/ep1192445",
        "title": "20",
        "type": 0,
        "type_title": "正片",
        "stat": {
            "coin": 63424,
            "dm": 29928,
            "favorite": 11893,
            "like": 78717,
            "reply": 3138,
            "share": 1538,
            "view": 14819594
        }
    },
    {
        "id": 1192446,
        "long_title": "杀了令郎偿饭钱",
        "share_url": "https://www.bilibili.com/bangumi/play/ep1192446",
        "title": "21",
        "type": 0,
        "type_title": "正片",
        "stat": {
            "coin": 63646,
            "dm": 49174,
            "favorite": 11540,
            "like": 77259,
            "reply": 3121,
            "share": 1617,
            "view": 14881146
        }
    },
    {
        "id": 1192447,
        "long_title": "延康大军",
        "share_url": "https://www.bilibili.com/bangumi/play/ep1192447",
        "title": "22",
        "type": 0,
        "type_title": "正片",
        "stat": {
            "coin": 69602,
            "dm": 54671,
            "favorite": 11986,
            "like": 81073,
            "reply": 2766,
            "share": 1685,
            "view": 14581600
        }
    },
    {
        "id": 1192448,
        "long_title": "天图太子",
        "share_url": "https://www.bilibili.com/bangumi/play/ep1192448",
        "title": "23",
        "type": 0,
        "type_title": "正片",
        "stat": {
            "coin": 81719,
            "dm": 50064,
            "favorite": 14159,
            "like": 92582,
            "reply": 3243,
            "share": 1922,
            "view": 14781410
        }
    },
    {
        "id": 1192450,
        "long_title": "太阳船",
        "share_url": "https://www.bilibili.com/bangumi/play/ep1192450",
        "title": "24",
        "type": 0,
        "type_title": "正片",
        "stat": {
            "coin": 70136,
            "dm": 26945,
            "favorite": 11012,
            "like": 80725,
            "reply": 3334,
            "share": 1519,
            "view": 14014525
        }
    },
    {
        "id": 1192451,
        "long_title": "牧日者",
        "share_url": "https://www.bilibili.com/bangumi/play/ep1192451",
        "title": "25",
        "type": 0,
        "type_title": "正片",
        "stat": {
            "coin": 55999,
            "dm": 58321,
            "favorite": 8798,
            "like": 68310,
            "reply": 2837,
            "share": 1117,
            "view": 12611570
        }
    },
    {
        "id": 1192470,
        "long_title": "暗界",
        "share_url": "https://www.bilibili.com/bangumi/play/ep1192470",
        "title": "26",
        "type": 0,
        "type_title": "正片",
        "stat": {
            "coin": 63158,
            "dm": 55200,
            "favorite": 9930,
            "like": 74287,
            "reply": 2336,
            "share": 1398,
            "view": 13544772
        }
    },
    {
        "id": 1524209,
        "long_title": "死者生界",
        "share_url": "https://www.bilibili.com/bangumi/play/ep1524209",
        "title": "27",
        "type": 0,
        "type_title": "正片",
        "stat": {
            "coin": 61139,
            "dm": 34978,
            "favorite": 9773,
            "like": 73993,
            "reply": 2120,
            "share": 1154,
            "view": 14138943
        }
    },
    {
        "id": 1524210,
        "long_title": "天魔众",
        "share_url": "https://www.bilibili.com/bangumi/play/ep1524210",
        "title": "28",
        "type": 0,
        "type_title": "正片",
        "stat": {
            "coin": 48991,
            "dm": 36905,
            "favorite": 9215,
            "like": 60952,
            "reply": 1795,
            "share": 1012,
            "view": 13343974
        }
    },
    {
        "id": 1524211,
        "long_title": "斩魍魉",
        "share_url": "https://www.bilibili.com/bangumi/play/ep1524211",
        "title": "29",
        "type": 0,
        "type_title": "正片",
        "stat": {
            "coin": 42733,
            "dm": 40842,
            "favorite": 6989,
            "like": 54847,
            "reply": 1714,
            "share": 874,
            "view": 12832123
        }
    },
    {
        "id": 1524212,
        "long_title": "月亮守",
        "share_url": "https://www.bilibili.com/bangumi/play/ep1524212",
        "title": "30",
        "type": 0,
        "type_title": "正片",
        "stat": {
            "coin": 39634,
            "dm": 19711,
            "favorite": 6267,
            "like": 52153,
            "reply": 1363,
            "share": 736,
            "view": 11560783
        }
    },
    {
        "id": 1524213,
        "long_title": "破关行",
        "share_url": "https://www.bilibili.com/bangumi/play/ep1524213",
        "title": "31",
        "type": 0,
        "type_title": "正片",
        "stat": {
            "coin": 40268,
            "dm": 31985,
            "favorite": 6066,
            "like": 51371,
            "reply": 1232,
            "share": 701,
            "view": 11699037
        }
    },
    {
        "id": 1524214,
        "long_title": "剑履山河",
        "share_url": "https://www.bilibili.com/bangumi/play/ep1524214",
        "title": "32",
        "type": 0,
        "type_title": "正片",
        "stat": {
            "coin": 49885,
            "dm": 37661,
            "favorite": 8412,
            "like": 62768,
            "reply": 2015,
            "share": 983,
            "view": 11518315
        }
    },
    {
        "id": 1524215,
        "long_title": "密水关",
        "share_url": "https://www.bilibili.com/bangumi/play/ep1524215",
        "title": "33",
        "type": 0,
        "type_title": "正片",
        "stat": {
            "coin": 46042,
            "dm": 33210,
            "favorite": 7354,
            "like": 58323,
            "reply": 1476,
            "share": 673,
            "view": 11467999
        }
    },
    {
        "id": 1524216,
        "long_title": "尸仙教",
        "share_url": "https://www.bilibili.com/bangumi/play/ep1524216",
        "title": "34",
        "type": 0,
        "type_title": "正片",
        "stat": {
            "coin": 44290,
            "dm": 56321,
            "favorite": 8159,
            "like": 57197,
            "reply": 2171,
            "share": 725,
            "view": 12102039
        }
    },
    {
        "id": 1524217,
        "long_title": "红尸蟞",
        "share_url": "https://www.bilibili.com/bangumi/play/ep1524217",
        "title": "35",
        "type": 0,
        "type_title": "正片",
        "stat": {
            "coin": 38777,
            "dm": 31705,
            "favorite": 5884,
            "like": 49318,
            "reply": 1941,
            "share": 557,
            "view": 10418441
        }
    },
    {
        "id": 1524218,
        "long_title": "坏蛋出村",
        "share_url": "https://www.bilibili.com/bangumi/play/ep1524218",
        "title": "36",
        "type": 0,
        "type_title": "正片",
        "stat": {
            "coin": 131923,
            "dm": 36613,
            "favorite": 21559,
            "like": 123400,
            "reply": 3204,
            "share": 764,
            "view": 11104732
        }
    },
    {
        "id": 1524219,
        "long_title": "驭龙门",
        "share_url": "https://www.bilibili.com/bangumi/play/ep1524219",
        "title": "37",
        "type": 0,
        "type_title": "正片",
        "stat": {
            "coin": 89742,
            "dm": 38764,
            "favorite": 14413,
            "like": 93742,
            "reply": 3679,
            "share": 785,
            "view": 11533350
        }
    },
    {
        "id": 1524220,
        "long_title": "水上天魔舞",
        "share_url": "https://www.bilibili.com/bangumi/play/ep1524220",
        "title": "38",
        "type": 0,
        "type_title": "正片",
        "stat": {
            "coin": 84651,
            "dm": 81124,
            "favorite": 14976,
            "like": 89797,
            "reply": 3211,
            "share": 767,
            "view": 11648306
        }
    },
    {
        "id": 1524221,
        "long_title": "太学院大考",
        "share_url": "https://www.bilibili.com/bangumi/play/ep1524221",
        "title": "39",
        "type": 0,
        "type_title": "正片",
        "stat": {
            "coin": 78406,
            "dm": 40712,
            "favorite": 11803,
            "like": 82376,
            "reply": 3253,
            "share": 706,
            "view": 10516016
        }
    },
    {
        "id": 1524222,
        "long_title": "延丰帝",
        "share_url": "https://www.bilibili.com/bangumi/play/ep1524222",
        "title": "40",
        "type": 0,
        "type_title": "正片",
        "stat": {
            "coin": 75133,
            "dm": 124470,
            "favorite": 12437,
            "like": 83800,
            "reply": 3816,
            "share": 794,
            "view": 11726766
        }
    },
    {
        "id": 1524223,
        "long_title": "祖师大考",
        "share_url": "https://www.bilibili.com/bangumi/play/ep1524223",
        "title": "41",
        "type": 0,
        "type_title": "正片",
        "stat": {
            "coin": 67232,
            "dm": 46377,
            "favorite": 10797,
            "like": 74436,
            "reply": 3182,
            "share": 618,
            "view": 10149005
        }
    },
    {
        "id": 1524224,
        "long_title": "千机毒",
        "share_url": "https://www.bilibili.com/bangumi/play/ep1524224",
        "title": "42",
        "type": 0,
        "type_title": "正片",
        "stat": {
            "coin": 69671,
            "dm": 62911,
            "favorite": 11423,
            "like": 81579,
            "reply": 3346,
            "share": 722,
            "view": 11010639
        }
    },
    {
        "id": 1524225,
        "long_title": "三大高手",
        "share_url": "https://www.bilibili.com/bangumi/play/ep1524225",
        "title": "43",
        "type": 0,
        "type_title": "正片",
        "stat": {
            "coin": 63652,
            "dm": 47255,
            "favorite": 9521,
            "like": 72727,
            "reply": 3068,
            "share": 581,
            "view": 9998194
        }
    },
    {
        "id": 1524226,
        "long_title": "道门堵门",
        "share_url": "https://www.bilibili.com/bangumi/play/ep1524226",
        "title": "44",
        "type": 0,
        "type_title": "正片",
        "stat": {
            "coin": 71928,
            "dm": 49685,
            "favorite": 9792,
            "like": 75497,
            "reply": 3460,
            "share": 622,
            "view": 9517189
        }
    },
    {
        "id": 1524227,
        "long_title": "绕剑式",
        "share_url": "https://www.bilibili.com/bangumi/play/ep1524227",
        "title": "45",
        "type": 0,
        "type_title": "正片",
        "stat": {
            "coin": 62533,
            "dm": 40183,
            "favorite": 8978,
            "like": 69591,
            "reply": 3240,
            "share": 577,
            "view": 9194824
        }
    },
    {
        "id": 1524228,
        "long_title": "少教主与道子",
        "share_url": "https://www.bilibili.com/bangumi/play/ep1524228",
        "title": "46",
        "type": 0,
        "type_title": "正片",
        "stat": {
            "coin": 69692,
            "dm": 50106,
            "favorite": 9934,
            "like": 75163,
            "reply": 3626,
            "share": 842,
            "view": 9563946
        }
    },
    {
        "id": 1524229,
        "long_title": "禅宗禅子",
        "share_url": "https://www.bilibili.com/bangumi/play/ep1524229",
        "title": "47",
        "type": 0,
        "type_title": "正片",
        "stat": {
            "coin": 57455,
            "dm": 34927,
            "favorite": 9105,
            "like": 65324,
            "reply": 3118,
            "share": 627,
            "view": 9515579
        }
    },
    {
        "id": 1524230,
        "long_title": "麻翻太学院",
        "share_url": "https://www.bilibili.com/bangumi/play/ep1524230",
        "title": "48",
        "type": 0,
        "type_title": "正片",
        "stat": {
            "coin": 57956,
            "dm": 32521,
            "favorite": 8467,
            "like": 65121,
            "reply": 2845,
            "share": 584,
            "view": 9020046
        }
    },
    {
        "id": 1524231,
        "long_title": "师兄师弟",
        "share_url": "https://www.bilibili.com/bangumi/play/ep1524231",
        "title": "49",
        "type": 0,
        "type_title": "正片",
        "stat": {
            "coin": 62569,
            "dm": 39669,
            "favorite": 9977,
            "like": 69679,
            "reply": 3141,
            "share": 672,
            "view": 9166954
        }
    },
    {
        "id": 1524232,
        "long_title": "武可汗",
        "share_url": "https://www.bilibili.com/bangumi/play/ep1524232",
        "title": "50",
        "type": 0,
        "type_title": "正片",
        "stat": {
            "coin": 63945,
            "dm": 42665,
            "favorite": 10174,
            "like": 70701,
            "reply": 2987,
            "share": 848,
            "view": 8549744
        }
    },
    {
        "id": 1524233,
        "long_title": "楼兰黄金宫",
        "share_url": "https://www.bilibili.com/bangumi/play/ep1524233",
        "title": "51",
        "type": 0,
        "type_title": "正片",
        "stat": {
            "coin": 56527,
            "dm": 38175,
            "favorite": 8649,
            "like": 64438,
            "reply": 2975,
            "share": 719,
            "view": 9170410
        }
    },
    {
        "id": 1524234,
        "long_title": "我，霸体",
        "share_url": "https://www.bilibili.com/bangumi/play/ep1524234",
        "title": "52",
        "type": 0,
        "type_title": "正片",
        "stat": {
            "coin": 59421,
            "dm": 38773,
            "favorite": 8702,
            "like": 64448,
            "reply": 3553,
            "share": 747,
            "view": 8816604
        }
    },
    {
        "id": 1524235,
        "long_title": "麻翻黄金宫",
        "share_url": "https://www.bilibili.com/bangumi/play/ep1524235",
        "title": "53",
        "type": 0,
        "type_title": "正片",
        "stat": {
            "coin": 60309,
            "dm": 37081,
            "favorite": 8830,
            "like": 64199,
            "reply": 3217,
            "share": 705,
            "view": 8480790
        }
    },
    {
        "id": 1524236,
        "long_title": "天可汗",
        "share_url": "https://www.bilibili.com/bangumi/play/ep1524236",
        "title": "54",
        "type": 0,
        "type_title": "正片",
        "stat": {
            "coin": 113011,
            "dm": 60811,
            "favorite": 17045,
            "like": 103674,
            "reply": 3283,
            "share": 820,
            "view": 9467264
        }
    },
    {
        "id": 1524237,
        "long_title": "转世圣童",
        "share_url": "https://www.bilibili.com/bangumi/play/ep1524237",
        "title": "55",
        "type": 0,
        "type_title": "正片",
        "stat": {
            "coin": 70057,
            "dm": 27570,
            "favorite": 10161,
            "like": 72219,
            "reply": 3153,
            "share": 668,
            "view": 8916768
        }
    },
    {
        "id": 1524238,
        "long_title": "圣教主登基",
        "share_url": "https://www.bilibili.com/bangumi/play/ep1524238",
        "title": "56",
        "type": 0,
        "type_title": "正片",
        "stat": {
            "coin": 69427,
            "dm": 39449,
            "favorite": 10613,
            "like": 71988,
            "reply": 3236,
            "share": 719,
            "view": 8307440
        }
    },
    {
        "id": 1524239,
        "long_title": "功法大一统",
        "share_url": "https://www.bilibili.com/bangumi/play/ep1524239",
        "title": "57",
        "type": 0,
        "type_title": "正片",
        "stat": {
            "coin": 54652,
            "dm": 59712,
            "favorite": 7987,
            "like": 59303,
            "reply": 2774,
            "share": 571,
            "view": 8049260
        }
    },
    {
        "id": 1524240,
        "long_title": "虫军",
        "share_url": "https://www.bilibili.com/bangumi/play/ep1524240",
        "title": "58",
        "type": 0,
        "type_title": "正片",
        "stat": {
            "coin": 52431,
            "dm": 21558,
            "favorite": 7111,
            "like": 55176,
            "reply": 2891,
            "share": 477,
            "view": 7195654
        }
    },
    {
        "id": 1524241,
        "long_title": "知行合一",
        "share_url": "https://www.bilibili.com/bangumi/play/ep1524241",
        "title": "59",
        "type": 0,
        "type_title": "正片",
        "stat": {
            "coin": 49743,
            "dm": 15902,
            "favorite": 7031,
            "like": 52705,
            "reply": 2884,
            "share": 526,
            "view": 6575359
        }
    },
    {
        "id": 1524242,
        "long_title": "阴间突袭",
        "share_url": "https://www.bilibili.com/bangumi/play/ep1524242",
        "title": "60",
        "type": 0,
        "type_title": "正片",
        "stat": {
            "coin": 49535,
            "dm": 20653,
            "favorite": 7855,
            "like": 52288,
            "reply": 3036,
            "share": 546,
            "view": 6632941
        }
    },
    {
        "id": 1524243,
        "long_title": "调鬼遣神",
        "share_url": "https://www.bilibili.com/bangumi/play/ep1524243",
        "title": "61",
        "type": 0,
        "type_title": "正片",
        "stat": {
            "coin": 39812,
            "dm": 16320,
            "favorite": 5557,
            "like": 41191,
            "reply": 2981,
            "share": 341,
            "view": 4439380
        }
    },
    {
        "id": 2375218,
        "long_title": "不断更年番，正在热播！",
        "share_url": "https://www.bilibili.com/bangumi/play/ep2375218",
        "title": "PV",
        "type": 1,
        "type_title": "预告",
        "stat": {
            "coin": 2496,
            "dm": 105,
            "favorite": 895,
            "like": 8361,
            "reply": 375,
            "share": 148,
            "view": 2576777
        }
    },
    {
        "id": 2307674,
        "long_title": "主创们私下竟然......",
        "share_url": "https://www.bilibili.com/bangumi/play/ep2307674",
        "title": "大青牛突击探班玄机科技！",
        "type": 1,
        "type_title": "预告",
        "stat": {
            "coin": 2368,
            "dm": 416,
            "favorite": 896,
            "like": 5883,
            "reply": 234,
            "share": 156,
            "view": 1829347
        }
    },
    {
        "id": 2303505,
        "long_title": "【牧神记动画】开播一周年 牧儿携友送福来~",
        "share_url": "https://www.bilibili.com/bangumi/play/ep2303505",
        "title": "祝贺牧神记开播一周年",
        "type": 1,
        "type_title": "预告",
        "stat": {
            "coin": 682,
            "dm": 45,
            "favorite": 172,
            "like": 1344,
            "reply": 67,
            "share": 27,
            "view": 423544
        }
    },
    {
        "id": 2302551,
        "long_title": "",
        "share_url": "https://www.bilibili.com/bangumi/play/ep2302551",
        "title": "一周年主创访谈",
        "type": 1,
        "type_title": "预告",
        "stat": {
            "coin": 1334,
            "dm": 308,
            "favorite": 373,
            "like": 3348,
            "reply": 343,
            "share": 79,
            "view": 403045
        }
    },
    {
        "id": 2325305,
        "long_title": "牧神记动画一周年 娱乐主播阿饼倾情献唱动画主题曲《式微》",
        "share_url": "https://www.bilibili.com/bangumi/play/ep2325305",
        "title": "【实力翻唱】",
        "type": 1,
        "type_title": "预告",
        "stat": {
            "coin": 240,
            "dm": 11,
            "favorite": 98,
            "like": 2014,
            "reply": 30,
            "share": 24,
            "view": 252776
        }
    },
    {
        "id": 2319911,
        "long_title": "和秦牧一起陪伴爷爷奶奶",
        "share_url": "https://www.bilibili.com/bangumi/play/ep2319911",
        "title": "【公益】",
        "type": 1,
        "type_title": "预告",
        "stat": {
            "coin": 286,
            "dm": 10,
            "favorite": 119,
            "like": 2923,
            "reply": 20,
            "share": 11,
            "view": 188954
        }
    },
    {
        "id": 2289528,
        "long_title": "",
        "share_url": "https://www.bilibili.com/bangumi/play/ep2289528",
        "title": "花絮3：一镜到底带你看遍黄金宫！",
        "type": 1,
        "type_title": "预告",
        "stat": {
            "coin": 600,
            "dm": 56,
            "favorite": 192,
            "like": 2537,
            "reply": 103,
            "share": 33,
            "view": 546735
        }
    },
    {
        "id": 2289468,
        "long_title": "",
        "share_url": "https://www.bilibili.com/bangumi/play/ep2289468",
        "title": "花絮2：黄金宫原画揭秘！细节满满",
        "type": 1,
        "type_title": "预告",
        "stat": {
            "coin": 409,
            "dm": 12,
            "favorite": 115,
            "like": 2074,
            "reply": 78,
            "share": 23,
            "view": 277553
        }
    },
    {
        "id": 2285823,
        "long_title": "",
        "share_url": "https://www.bilibili.com/bangumi/play/ep2285823",
        "title": "花絮1：带你光顾秦牧的房间！",
        "type": 1,
        "type_title": "预告",
        "stat": {
            "coin": 364,
            "dm": 37,
            "favorite": 164,
            "like": 3037,
            "reply": 93,
            "share": 16,
            "view": 272746
        }
    },
    {
        "id": 2301846,
        "long_title": "暨大墟年会现场回顾",
        "share_url": "https://www.bilibili.com/bangumi/play/ep2301846",
        "title": "【牧神记动画】一周年庆典",
        "type": 1,
        "type_title": "预告",
        "stat": {
            "coin": 115,
            "dm": 8,
            "favorite": 37,
            "like": 271,
            "reply": 32,
            "share": 14,
            "view": 143070
        }
    },
    {
        "id": 2274133,
        "long_title": "黄霄雲为牧神记动画倾情打call",
        "share_url": "https://www.bilibili.com/bangumi/play/ep2274133",
        "title": "黄霄雲祝福视频",
        "type": 1,
        "type_title": "预告",
        "stat": {
            "coin": 282,
            "dm": 26,
            "favorite": 98,
            "like": 2254,
            "reply": 122,
            "share": 45,
            "view": 229042
        }
    },
    {
        "id": 2178878,
        "long_title": "",
        "share_url": "https://www.bilibili.com/bangumi/play/ep2178878",
        "title": "黄金宫篇PV",
        "type": 1,
        "type_title": "预告",
        "stat": {
            "coin": 1931,
            "dm": 181,
            "favorite": 718,
            "like": 5132,
            "reply": 298,
            "share": 148,
            "view": 2478879
        }
    },
    {
        "id": 2051707,
        "long_title": "吴垚滔现场演绎主题曲《天外的天》",
        "share_url": "https://www.bilibili.com/bangumi/play/ep2051707",
        "title": "【独家】豫园×牧神记动画",
        "type": 1,
        "type_title": "预告",
        "stat": {
            "coin": 2408,
            "dm": 472,
            "favorite": 1363,
            "like": 6431,
            "reply": 326,
            "share": 149,
            "view": 4151171
        }
    },
    {
        "id": 1881307,
        "long_title": "",
        "share_url": "https://www.bilibili.com/bangumi/play/ep1881307",
        "title": "灵毓秀宫装PV",
        "type": 1,
        "type_title": "预告",
        "stat": {
            "coin": 2669,
            "dm": 254,
            "favorite": 1506,
            "like": 6694,
            "reply": 304,
            "share": 247,
            "view": 3591088
        }
    },
    {
        "id": 1836776,
        "long_title": "",
        "share_url": "https://www.bilibili.com/bangumi/play/ep1836776",
        "title": "太学院篇PV",
        "type": 1,
        "type_title": "预告",
        "stat": {
            "coin": 1678,
            "dm": 168,
            "favorite": 749,
            "like": 4323,
            "reply": 259,
            "share": 123,
            "view": 1821293
        }
    },
    {
        "id": 1736860,
        "long_title": "",
        "share_url": "https://www.bilibili.com/bangumi/play/ep1736860",
        "title": "秦牧新造型PV",
        "type": 1,
        "type_title": "预告",
        "stat": {
            "coin": 2000,
            "dm": 162,
            "favorite": 790,
            "like": 4812,
            "reply": 291,
            "share": 130,
            "view": 2642092
        }
    },
    {
        "id": 1585302,
        "long_title": "",
        "share_url": "https://www.bilibili.com/bangumi/play/ep1585302",
        "title": "年番全新PV",
        "type": 1,
        "type_title": "预告",
        "stat": {
            "coin": 2234,
            "dm": 223,
            "favorite": 572,
            "like": 5803,
            "reply": 577,
            "share": 293,
            "view": 1360301
        }
    },
    {
        "id": 1466323,
        "long_title": "",
        "share_url": "https://www.bilibili.com/bangumi/play/ep1466323",
        "title": "灵毓秀角色pv",
        "type": 1,
        "type_title": "预告",
        "stat": {
            "coin": 5260,
            "dm": 400,
            "favorite": 2150,
            "like": 9374,
            "reply": 599,
            "share": 360,
            "view": 5628010
        }
    },
    {
        "id": 1451451,
        "long_title": "",
        "share_url": "https://www.bilibili.com/bangumi/play/ep1451451",
        "title": "少年版秦牧角色PV",
        "type": 1,
        "type_title": "预告",
        "stat": {
            "coin": 2489,
            "dm": 207,
            "favorite": 1066,
            "like": 5303,
            "reply": 446,
            "share": 262,
            "view": 2610822
        }
    },
    {
        "id": 1225107,
        "long_title": "",
        "share_url": "https://www.bilibili.com/bangumi/play/ep1225107",
        "title": "苏绣纪录花絮特辑上线！",
        "type": 1,
        "type_title": "预告",
        "stat": {
            "coin": 4428,
            "dm": 482,
            "favorite": 1685,
            "like": 8192,
            "reply": 282,
            "share": 381,
            "view": 3674384
        }
    },
    {
        "id": 1214624,
        "long_title": "与其跪神乞怜，不如站着，做自己的神",
        "share_url": "https://www.bilibili.com/bangumi/play/ep1214624",
        "title": "年番PV",
        "type": 1,
        "type_title": "预告",
        "stat": {
            "coin": 3898,
            "dm": 315,
            "favorite": 1328,
            "like": 7230,
            "reply": 578,
            "share": 403,
            "view": 2583427
        }
    },
    {
        "id": 1112145,
        "long_title": "",
        "share_url": "https://www.bilibili.com/bangumi/play/ep1112145",
        "title": "开播PV",
        "type": 1,
        "type_title": "预告",
        "stat": {
            "coin": 3438,
            "dm": 377,
            "favorite": 1493,
            "like": 5896,
            "reply": 643,
            "share": 623,
            "view": 2675358
        }
    },
    {
        "id": 1112144,
        "long_title": "",
        "share_url": "https://www.bilibili.com/bangumi/play/ep1112144",
        "title": "秦牧角色PV",
        "type": 1,
        "type_title": "预告",
        "stat": {
            "coin": 1081,
            "dm": 214,
            "favorite": 414,
            "like": 2665,
            "reply": 355,
            "share": 168,
            "view": 1308458
        }
    },
    {
        "id": 1112143,
        "long_title": "",
        "share_url": "https://www.bilibili.com/bangumi/play/ep1112143",
        "title": "残老村九老群像PV",
        "type": 1,
        "type_title": "预告",
        "stat": {
            "coin": 1068,
            "dm": 189,
            "favorite": 517,
            "like": 2849,
            "reply": 330,
            "share": 237,
            "view": 1159986
        }
    },
    {
        "id": 1112142,
        "long_title": "",
        "share_url": "https://www.bilibili.com/bangumi/play/ep1112142",
        "title": "司幼幽角色PV",
        "type": 1,
        "type_title": "预告",
        "stat": {
            "coin": 843,
            "dm": 94,
            "favorite": 313,
            "like": 2393,
            "reply": 241,
            "share": 171,
            "view": 1066030
        }
    },
    {
        "id": 838379,
        "long_title": "",
        "share_url": "https://www.bilibili.com/bangumi/play/ep838379",
        "title": "场景PV公开！",
        "type": 1,
        "type_title": "预告",
        "stat": {
            "coin": 1426,
            "dm": 340,
            "favorite": 744,
            "like": 3630,
            "reply": 513,
            "share": 477,
            "view": 1174513
        }
    },
    {
        "id": 1112806,
        "long_title": "",
        "share_url": "https://www.bilibili.com/bangumi/play/ep1112806",
        "title": "陈楚生为牧神记开播倾情打call",
        "type": 1,
        "type_title": "预告",
        "stat": {
            "coin": 1062,
            "dm": 154,
            "favorite": 485,
            "like": 2414,
            "reply": 147,
            "share": 106,
            "view": 1184335
        }
    },
    {
        "id": 836715,
        "long_title": "放牛娃的传奇人生即将开始",
        "share_url": "https://www.bilibili.com/bangumi/play/ep836715",
        "title": "牧神记定档10月27日！",
        "type": 1,
        "type_title": "预告",
        "stat": {
            "coin": 2006,
            "dm": 706,
            "favorite": 1215,
            "like": 5891,
            "reply": 1374,
            "share": 1382,
            "view": 1569676
        }
    },
    {
        "id": 775978,
        "long_title": "放牧诸神，为芸芸众生而战！",
        "share_url": "https://www.bilibili.com/bangumi/play/ep775978",
        "title": "PV",
        "type": 1,
        "type_title": "预告",
        "stat": {
            "coin": 5253,
            "dm": 1760,
            "favorite": 3497,
            "like": 20787,
            "reply": 4564,
            "share": 3260,
            "view": 2387346
        }
    },
    {
        "id": 1113958,
        "long_title": "",
        "share_url": "https://www.bilibili.com/bangumi/play/ep1113958",
        "title": "片尾曲《不息》乐队版MV",
        "type": 1,
        "type_title": "预告",
        "stat": {
            "coin": 2812,
            "dm": 257,
            "favorite": 1612,
            "like": 4621,
            "reply": 275,
            "share": 185,
            "view": 2125449
        }
    },
    {
        "id": 1112196,
        "long_title": "",
        "share_url": "https://www.bilibili.com/bangumi/play/ep1112196",
        "title": "第2集预告",
        "type": 1,
        "type_title": "预告",
        "stat": {
            "coin": 647,
            "dm": 70,
            "favorite": 262,
            "like": 1576,
            "reply": 56,
            "share": 39,
            "view": 985362
        }
    },
    {
        "id": 1112279,
        "long_title": "",
        "share_url": "https://www.bilibili.com/bangumi/play/ep1112279",
        "title": "第3集预告",
        "type": 1,
        "type_title": "预告",
        "stat": {
            "coin": 4546,
            "dm": 492,
            "favorite": 1314,
            "like": 7622,
            "reply": 670,
            "share": 155,
            "view": 2001469
        }
    },
    {
        "id": 1112280,
        "long_title": "",
        "share_url": "https://www.bilibili.com/bangumi/play/ep1112280",
        "title": "第4集预告",
        "type": 1,
        "type_title": "预告",
        "stat": {
            "coin": 2846,
            "dm": 274,
            "favorite": 840,
            "like": 5717,
            "reply": 300,
            "share": 110,
            "view": 2076477
        }
    },
    {
        "id": 1112281,
        "long_title": "",
        "share_url": "https://www.bilibili.com/bangumi/play/ep1112281",
        "title": "第5集预告",
        "type": 1,
        "type_title": "预告",
        "stat": {
            "coin": 3503,
            "dm": 256,
            "favorite": 939,
            "like": 6533,
            "reply": 366,
            "share": 98,
            "view": 2316756
        }
    },
    {
        "id": 1112282,
        "long_title": "",
        "share_url": "https://www.bilibili.com/bangumi/play/ep1112282",
        "title": "第6集预告",
        "type": 1,
        "type_title": "预告",
        "stat": {
            "coin": 3561,
            "dm": 172,
            "favorite": 906,
            "like": 6781,
            "reply": 399,
            "share": 136,
            "view": 2271525
        }
    },
    {
        "id": 1112283,
        "long_title": "",
        "share_url": "https://www.bilibili.com/bangumi/play/ep1112283",
        "title": "第7集预告",
        "type": 1,
        "type_title": "预告",
        "stat": {
            "coin": 3609,
            "dm": 245,
            "favorite": 841,
            "like": 6649,
            "reply": 269,
            "share": 84,
            "view": 2261274
        }
    },
    {
        "id": 1112284,
        "long_title": "",
        "share_url": "https://www.bilibili.com/bangumi/play/ep1112284",
        "title": "第8集预告",
        "type": 1,
        "type_title": "预告",
        "stat": {
            "coin": 4611,
            "dm": 215,
            "favorite": 995,
            "like": 7429,
            "reply": 267,
            "share": 127,
            "view": 2349877
        }
    },
    {
        "id": 1112285,
        "long_title": "",
        "share_url": "https://www.bilibili.com/bangumi/play/ep1112285",
        "title": "第9集预告",
        "type": 1,
        "type_title": "预告",
        "stat": {
            "coin": 3597,
            "dm": 152,
            "favorite": 790,
            "like": 6314,
            "reply": 292,
            "share": 90,
            "view": 2104759
        }
    },
    {
        "id": 1112286,
        "long_title": "",
        "share_url": "https://www.bilibili.com/bangumi/play/ep1112286",
        "title": "第10集预告",
        "type": 1,
        "type_title": "预告",
        "stat": {
            "coin": 4252,
            "dm": 110,
            "favorite": 882,
            "like": 7311,
            "reply": 341,
            "share": 103,
            "view": 2195840
        }
    },
    {
        "id": 1112287,
        "long_title": "",
        "share_url": "https://www.bilibili.com/bangumi/play/ep1112287",
        "title": "第11集预告",
        "type": 1,
        "type_title": "预告",
        "stat": {
            "coin": 3188,
            "dm": 158,
            "favorite": 837,
            "like": 6439,
            "reply": 312,
            "share": 103,
            "view": 2396324
        }
    },
    {
        "id": 1112288,
        "long_title": "",
        "share_url": "https://www.bilibili.com/bangumi/play/ep1112288",
        "title": "第12集预告",
        "type": 1,
        "type_title": "预告",
        "stat": {
            "coin": 3574,
            "dm": 233,
            "favorite": 709,
            "like": 6746,
            "reply": 230,
            "share": 115,
            "view": 2173139
        }
    },
    {
        "id": 1112289,
        "long_title": "",
        "share_url": "https://www.bilibili.com/bangumi/play/ep1112289",
        "title": "第13集预告",
        "type": 1,
        "type_title": "预告",
        "stat": {
            "coin": 2596,
            "dm": 109,
            "favorite": 682,
            "like": 5719,
            "reply": 227,
            "share": 77,
            "view": 2146538
        }
    },
    {
        "id": 1112290,
        "long_title": "",
        "share_url": "https://www.bilibili.com/bangumi/play/ep1112290",
        "title": "第14集预告",
        "type": 1,
        "type_title": "预告",
        "stat": {
            "coin": 4849,
            "dm": 223,
            "favorite": 2592,
            "like": 9148,
            "reply": 475,
            "share": 217,
            "view": 5942102
        }
    },
    {
        "id": 1112291,
        "long_title": "",
        "share_url": "https://www.bilibili.com/bangumi/play/ep1112291",
        "title": "第15集预告",
        "type": 1,
        "type_title": "预告",
        "stat": {
            "coin": 3393,
            "dm": 162,
            "favorite": 1198,
            "like": 6905,
            "reply": 399,
            "share": 106,
            "view": 3678201
        }
    },
    {
        "id": 1112292,
        "long_title": "",
        "share_url": "https://www.bilibili.com/bangumi/play/ep1112292",
        "title": "第16集预告",
        "type": 1,
        "type_title": "预告",
        "stat": {
            "coin": 3618,
            "dm": 125,
            "favorite": 935,
            "like": 7289,
            "reply": 348,
            "share": 103,
            "view": 3081486
        }
    },
    {
        "id": 1112293,
        "long_title": "",
        "share_url": "https://www.bilibili.com/bangumi/play/ep1112293",
        "title": "第17集预告",
        "type": 1,
        "type_title": "预告",
        "stat": {
            "coin": 3804,
            "dm": 201,
            "favorite": 976,
            "like": 7546,
            "reply": 376,
            "share": 115,
            "view": 3018903
        }
    },
    {
        "id": 1112294,
        "long_title": "",
        "share_url": "https://www.bilibili.com/bangumi/play/ep1112294",
        "title": "第18集预告",
        "type": 1,
        "type_title": "预告",
        "stat": {
            "coin": 4320,
            "dm": 244,
            "favorite": 1042,
            "like": 8583,
            "reply": 633,
            "share": 279,
            "view": 3014367
        }
    },
    {
        "id": 1112295,
        "long_title": "",
        "share_url": "https://www.bilibili.com/bangumi/play/ep1112295",
        "title": "第19集预告",
        "type": 1,
        "type_title": "预告",
        "stat": {
            "coin": 5976,
            "dm": 188,
            "favorite": 1533,
            "like": 10774,
            "reply": 651,
            "share": 235,
            "view": 3734173
        }
    },
    {
        "id": 1112296,
        "long_title": "",
        "share_url": "https://www.bilibili.com/bangumi/play/ep1112296",
        "title": "第20集预告",
        "type": 1,
        "type_title": "预告",
        "stat": {
            "coin": 4457,
            "dm": 249,
            "favorite": 1252,
            "like": 8873,
            "reply": 558,
            "share": 354,
            "view": 3317598
        }
    },
    {
        "id": 1112297,
        "long_title": "",
        "share_url": "https://www.bilibili.com/bangumi/play/ep1112297",
        "title": "第21集预告",
        "type": 1,
        "type_title": "预告",
        "stat": {
            "coin": 4383,
            "dm": 227,
            "favorite": 1034,
            "like": 8916,
            "reply": 580,
            "share": 220,
            "view": 3393640
        }
    },
    {
        "id": 1112298,
        "long_title": "",
        "share_url": "https://www.bilibili.com/bangumi/play/ep1112298",
        "title": "第22集预告",
        "type": 1,
        "type_title": "预告",
        "stat": {
            "coin": 4858,
            "dm": 396,
            "favorite": 1139,
            "like": 9311,
            "reply": 620,
            "share": 135,
            "view": 3286355
        }
    },
    {
        "id": 1112299,
        "long_title": "",
        "share_url": "https://www.bilibili.com/bangumi/play/ep1112299",
        "title": "第23集预告",
        "type": 1,
        "type_title": "预告",
        "stat": {
            "coin": 4664,
            "dm": 209,
            "favorite": 967,
            "like": 9145,
            "reply": 722,
            "share": 233,
            "view": 2996776
        }
    },
    {
        "id": 1112300,
        "long_title": "",
        "share_url": "https://www.bilibili.com/bangumi/play/ep1112300",
        "title": "第24集预告",
        "type": 1,
        "type_title": "预告",
        "stat": {
            "coin": 5584,
            "dm": 449,
            "favorite": 967,
            "like": 10062,
            "reply": 1048,
            "share": 201,
            "view": 3094519
        }
    },
    {
        "id": 1112301,
        "long_title": "年番定档4月20日",
        "share_url": "https://www.bilibili.com/bangumi/play/ep1112301",
        "title": "第25集预告",
        "type": 1,
        "type_title": "预告",
        "stat": {
            "coin": 10172,
            "dm": 502,
            "favorite": 1808,
            "like": 15201,
            "reply": 953,
            "share": 452,
            "view": 3532944
        }
    },
    {
        "id": 1112302,
        "long_title": "",
        "share_url": "https://www.bilibili.com/bangumi/play/ep1112302",
        "title": "第26集预告",
        "type": 1,
        "type_title": "预告",
        "stat": {
            "coin": 4135,
            "dm": 222,
            "favorite": 751,
            "like": 8462,
            "reply": 458,
            "share": 113,
            "view": 2586586
        }
    },
    {
        "id": 1529070,
        "long_title": "",
        "share_url": "https://www.bilibili.com/bangumi/play/ep1529070",
        "title": "第27集预告",
        "type": 1,
        "type_title": "预告",
        "stat": {
            "coin": 4887,
            "dm": 270,
            "favorite": 819,
            "like": 9442,
            "reply": 529,
            "share": 113,
            "view": 2785649
        }
    },
    {
        "id": 1529071,
        "long_title": "",
        "share_url": "https://www.bilibili.com/bangumi/play/ep1529071",
        "title": "第28集预告",
        "type": 1,
        "type_title": "预告",
        "stat": {
            "coin": 3527,
            "dm": 188,
            "favorite": 609,
            "like": 7545,
            "reply": 460,
            "share": 109,
            "view": 2517641
        }
    },
    {
        "id": 1529072,
        "long_title": "",
        "share_url": "https://www.bilibili.com/bangumi/play/ep1529072",
        "title": "第29集预告",
        "type": 1,
        "type_title": "预告",
        "stat": {
            "coin": 3079,
            "dm": 150,
            "favorite": 559,
            "like": 6780,
            "reply": 313,
            "share": 79,
            "view": 2250271
        }
    },
    {
        "id": 1529073,
        "long_title": "",
        "share_url": "https://www.bilibili.com/bangumi/play/ep1529073",
        "title": "第30集预告",
        "type": 1,
        "type_title": "预告",
        "stat": {
            "coin": 2840,
            "dm": 165,
            "favorite": 555,
            "like": 6718,
            "reply": 388,
            "share": 86,
            "view": 2277639
        }
    },
    {
        "id": 1529074,
        "long_title": "",
        "share_url": "https://www.bilibili.com/bangumi/play/ep1529074",
        "title": "第31集预告",
        "type": 1,
        "type_title": "预告",
        "stat": {
            "coin": 2538,
            "dm": 147,
            "favorite": 444,
            "like": 6016,
            "reply": 296,
            "share": 62,
            "view": 2088042
        }
    },
    {
        "id": 1529075,
        "long_title": "",
        "share_url": "https://www.bilibili.com/bangumi/play/ep1529075",
        "title": "第32集预告",
        "type": 1,
        "type_title": "预告",
        "stat": {
            "coin": 2692,
            "dm": 185,
            "favorite": 564,
            "like": 6382,
            "reply": 340,
            "share": 67,
            "view": 2006964
        }
    },
    {
        "id": 1529076,
        "long_title": "",
        "share_url": "https://www.bilibili.com/bangumi/play/ep1529076",
        "title": "第33集预告",
        "type": 1,
        "type_title": "预告",
        "stat": {
            "coin": 2917,
            "dm": 174,
            "favorite": 566,
            "like": 6579,
            "reply": 318,
            "share": 75,
            "view": 2154049
        }
    },
    {
        "id": 1529077,
        "long_title": "",
        "share_url": "https://www.bilibili.com/bangumi/play/ep1529077",
        "title": "第34集预告",
        "type": 1,
        "type_title": "预告",
        "stat": {
            "coin": 2542,
            "dm": 161,
            "favorite": 488,
            "like": 5886,
            "reply": 248,
            "share": 63,
            "view": 1851504
        }
    },
    {
        "id": 1529078,
        "long_title": "",
        "share_url": "https://www.bilibili.com/bangumi/play/ep1529078",
        "title": "第35集预告",
        "type": 1,
        "type_title": "预告",
        "stat": {
            "coin": 2683,
            "dm": 179,
            "favorite": 512,
            "like": 6248,
            "reply": 415,
            "share": 60,
            "view": 2099894
        }
    },
    {
        "id": 1529079,
        "long_title": "",
        "share_url": "https://www.bilibili.com/bangumi/play/ep1529079",
        "title": "第36集预告",
        "type": 1,
        "type_title": "预告",
        "stat": {
            "coin": 2918,
            "dm": 231,
            "favorite": 534,
            "like": 6590,
            "reply": 383,
            "share": 68,
            "view": 2110838
        }
    },
    {
        "id": 1529080,
        "long_title": "",
        "share_url": "https://www.bilibili.com/bangumi/play/ep1529080",
        "title": "第37集预告",
        "type": 1,
        "type_title": "预告",
        "stat": {
            "coin": 3128,
            "dm": 161,
            "favorite": 559,
            "like": 6448,
            "reply": 250,
            "share": 72,
            "view": 1955220
        }
    },
    {
        "id": 1529081,
        "long_title": "",
        "share_url": "https://www.bilibili.com/bangumi/play/ep1529081",
        "title": "第38集预告",
        "type": 1,
        "type_title": "预告",
        "stat": {
            "coin": 3564,
            "dm": 269,
            "favorite": 680,
            "like": 7054,
            "reply": 545,
            "share": 60,
            "view": 1940923
        }
    },
    {
        "id": 1529082,
        "long_title": "",
        "share_url": "https://www.bilibili.com/bangumi/play/ep1529082",
        "title": "第39集预告",
        "type": 1,
        "type_title": "预告",
        "stat": {
            "coin": 3496,
            "dm": 208,
            "favorite": 658,
            "like": 7259,
            "reply": 316,
            "share": 64,
            "view": 2209940
        }
    },
    {
        "id": 1529083,
        "long_title": "",
        "share_url": "https://www.bilibili.com/bangumi/play/ep1529083",
        "title": "第40集预告",
        "type": 1,
        "type_title": "预告",
        "stat": {
            "coin": 4587,
            "dm": 382,
            "favorite": 899,
            "like": 9798,
            "reply": 608,
            "share": 84,
            "view": 3032661
        }
    },
    {
        "id": 1529084,
        "long_title": "",
        "share_url": "https://www.bilibili.com/bangumi/play/ep1529084",
        "title": "第41集预告",
        "type": 1,
        "type_title": "预告",
        "stat": {
            "coin": 3784,
            "dm": 447,
            "favorite": 807,
            "like": 8295,
            "reply": 632,
            "share": 77,
            "view": 2513725
        }
    },
    {
        "id": 1529085,
        "long_title": "",
        "share_url": "https://www.bilibili.com/bangumi/play/ep1529085",
        "title": "第42集预告",
        "type": 1,
        "type_title": "预告",
        "stat": {
            "coin": 3825,
            "dm": 522,
            "favorite": 779,
            "like": 8454,
            "reply": 600,
            "share": 62,
            "view": 2856613
        }
    },
    {
        "id": 1529086,
        "long_title": "",
        "share_url": "https://www.bilibili.com/bangumi/play/ep1529086",
        "title": "第43集预告",
        "type": 1,
        "type_title": "预告",
        "stat": {
            "coin": 3521,
            "dm": 351,
            "favorite": 717,
            "like": 7722,
            "reply": 329,
            "share": 68,
            "view": 2466376
        }
    },
    {
        "id": 1529087,
        "long_title": "",
        "share_url": "https://www.bilibili.com/bangumi/play/ep1529087",
        "title": "第44集预告",
        "type": 1,
        "type_title": "预告",
        "stat": {
            "coin": 3668,
            "dm": 476,
            "favorite": 761,
            "like": 8335,
            "reply": 537,
            "share": 69,
            "view": 2708287
        }
    },
    {
        "id": 1529088,
        "long_title": "",
        "share_url": "https://www.bilibili.com/bangumi/play/ep1529088",
        "title": "第45集预告",
        "type": 1,
        "type_title": "预告",
        "stat": {
            "coin": 4323,
            "dm": 465,
            "favorite": 1022,
            "like": 9591,
            "reply": 719,
            "share": 80,
            "view": 3401620
        }
    },
    {
        "id": 1529089,
        "long_title": "",
        "share_url": "https://www.bilibili.com/bangumi/play/ep1529089",
        "title": "第46集预告",
        "type": 1,
        "type_title": "预告",
        "stat": {
            "coin": 4379,
            "dm": 541,
            "favorite": 977,
            "like": 9817,
            "reply": 987,
            "share": 75,
            "view": 3503852
        }
    },
    {
        "id": 1529090,
        "long_title": "",
        "share_url": "https://www.bilibili.com/bangumi/play/ep1529090",
        "title": "第47集预告",
        "type": 1,
        "type_title": "预告",
        "stat": {
            "coin": 4034,
            "dm": 396,
            "favorite": 743,
            "like": 8492,
            "reply": 907,
            "share": 81,
            "view": 2655087
        }
    },
    {
        "id": 1529091,
        "long_title": "",
        "share_url": "https://www.bilibili.com/bangumi/play/ep1529091",
        "title": "第48集预告",
        "type": 1,
        "type_title": "预告",
        "stat": {
            "coin": 3942,
            "dm": 284,
            "favorite": 796,
            "like": 8947,
            "reply": 706,
            "share": 70,
            "view": 3270192
        }
    },
    {
        "id": 1529092,
        "long_title": "",
        "share_url": "https://www.bilibili.com/bangumi/play/ep1529092",
        "title": "第49集预告",
        "type": 1,
        "type_title": "预告",
        "stat": {
            "coin": 3626,
            "dm": 258,
            "favorite": 711,
            "like": 8040,
            "reply": 495,
            "share": 84,
            "view": 2596152
        }
    },
    {
        "id": 1529093,
        "long_title": "",
        "share_url": "https://www.bilibili.com/bangumi/play/ep1529093",
        "title": "第50集预告",
        "type": 1,
        "type_title": "预告",
        "stat": {
            "coin": 4515,
            "dm": 401,
            "favorite": 828,
            "like": 8514,
            "reply": 603,
            "share": 70,
            "view": 2082131
        }
    },
    {
        "id": 1529094,
        "long_title": "",
        "share_url": "https://www.bilibili.com/bangumi/play/ep1529094",
        "title": "第51集预告",
        "type": 1,
        "type_title": "预告",
        "stat": {
            "coin": 3898,
            "dm": 255,
            "favorite": 764,
            "like": 8610,
            "reply": 562,
            "share": 78,
            "view": 2550521
        }
    },
    {
        "id": 1529095,
        "long_title": "",
        "share_url": "https://www.bilibili.com/bangumi/play/ep1529095",
        "title": "第52集预告",
        "type": 1,
        "type_title": "预告",
        "stat": {
            "coin": 4553,
            "dm": 541,
            "favorite": 907,
            "like": 9395,
            "reply": 843,
            "share": 82,
            "view": 3187664
        }
    },
    {
        "id": 1529096,
        "long_title": "",
        "share_url": "https://www.bilibili.com/bangumi/play/ep1529096",
        "title": "第53集预告",
        "type": 1,
        "type_title": "预告",
        "stat": {
            "coin": 4364,
            "dm": 384,
            "favorite": 788,
            "like": 9247,
            "reply": 688,
            "share": 89,
            "view": 2965446
        }
    },
    {
        "id": 1529097,
        "long_title": "",
        "share_url": "https://www.bilibili.com/bangumi/play/ep1529097",
        "title": "第54集预告",
        "type": 1,
        "type_title": "预告",
        "stat": {
            "coin": 4505,
            "dm": 428,
            "favorite": 763,
            "like": 10026,
            "reply": 712,
            "share": 68,
            "view": 3166266
        }
    },
    {
        "id": 1529098,
        "long_title": "",
        "share_url": "https://www.bilibili.com/bangumi/play/ep1529098",
        "title": "第55集预告",
        "type": 1,
        "type_title": "预告",
        "stat": {
            "coin": 5689,
            "dm": 285,
            "favorite": 1006,
            "like": 9576,
            "reply": 601,
            "share": 68,
            "view": 2607512
        }
    },
    {
        "id": 1529099,
        "long_title": "",
        "share_url": "https://www.bilibili.com/bangumi/play/ep1529099",
        "title": "第56集预告",
        "type": 1,
        "type_title": "预告",
        "stat": {
            "coin": 5199,
            "dm": 289,
            "favorite": 821,
            "like": 9576,
            "reply": 492,
            "share": 85,
            "view": 2512963
        }
    },
    {
        "id": 1529100,
        "long_title": "",
        "share_url": "https://www.bilibili.com/bangumi/play/ep1529100",
        "title": "第57集预告",
        "type": 1,
        "type_title": "预告",
        "stat": {
            "coin": 5212,
            "dm": 253,
            "favorite": 855,
            "like": 9602,
            "reply": 817,
            "share": 72,
            "view": 2675364
        }
    },
    {
        "id": 1529101,
        "long_title": "",
        "share_url": "https://www.bilibili.com/bangumi/play/ep1529101",
        "title": "第58集预告",
        "type": 1,
        "type_title": "预告",
        "stat": {
            "coin": 4131,
            "dm": 251,
            "favorite": 717,
            "like": 8582,
            "reply": 378,
            "share": 82,
            "view": 2650313
        }
    },
    {
        "id": 1529102,
        "long_title": "",
        "share_url": "https://www.bilibili.com/bangumi/play/ep1529102",
        "title": "第59集预告",
        "type": 1,
        "type_title": "预告",
        "stat": {
            "coin": 5485,
            "dm": 257,
            "favorite": 773,
            "like": 9459,
            "reply": 473,
            "share": 60,
            "view": 2406031
        }
    },
    {
        "id": 1529103,
        "long_title": "",
        "share_url": "https://www.bilibili.com/bangumi/play/ep1529103",
        "title": "第60集预告",
        "type": 1,
        "type_title": "预告",
        "stat": {
            "coin": 3896,
            "dm": 251,
            "favorite": 651,
            "like": 8385,
            "reply": 467,
            "share": 68,
            "view": 2332528
        }
    },
    {
        "id": 1529104,
        "long_title": "",
        "share_url": "https://www.bilibili.com/bangumi/play/ep1529104",
        "title": "第61集预告",
        "type": 1,
        "type_title": "预告",
        "stat": {
            "coin": 4314,
            "dm": 238,
            "favorite": 730,
            "like": 8792,
            "reply": 366,
            "share": 74,
            "view": 2301384
        }
    },
    {
        "id": 1529105,
        "long_title": "",
        "share_url": "https://www.bilibili.com/bangumi/play/ep1529105",
        "title": "第62集预告",
        "type": 1,
        "type_title": "预告",
        "stat": {
            "coin": 3387,
            "dm": 245,
            "favorite": 524,
            "like": 7879,
            "reply": 549,
            "share": 52,
            "view": 1713469
        }
    },
    {
        "id": 2265606,
        "long_title": "",
        "share_url": "https://www.bilibili.com/bangumi/play/ep2265606",
        "title": "【独家】牧神记全新片尾曲《式微》",
        "type": 2,
        "type_title": "特别花絮",
        "stat": {
            "coin": 3065,
            "dm": 302,
            "favorite": 1228,
            "like": 7087,
            "reply": 625,
            "share": 280,
            "view": 1917079
        }
    },
    {
        "id": 2291407,
        "long_title": "",
        "share_url": "https://www.bilibili.com/bangumi/play/ep2291407",
        "title": "牧神记片尾曲《式微》制作花絮公开",
        "type": 2,
        "type_title": "特别花絮",
        "stat": {
            "coin": 225,
            "dm": 35,
            "favorite": 95,
            "like": 842,
            "reply": 41,
            "share": 46,
            "view": 187083
        }
    },
    {
        "id": 2265602,
        "long_title": "",
        "share_url": "https://www.bilibili.com/bangumi/play/ep2265602",
        "title": "【独家】牧神记OP全新画面发布",
        "type": 2,
        "type_title": "特别花絮",
        "stat": {
            "coin": 1092,
            "dm": 149,
            "favorite": 477,
            "like": 3909,
            "reply": 381,
            "share": 116,
            "view": 431683
        }
    },
    {
        "id": 1587548,
        "long_title": "《天外的天》",
        "share_url": "https://www.bilibili.com/bangumi/play/ep1587548",
        "title": "年番新画面OP",
        "type": 2,
        "type_title": "特别花絮",
        "stat": {
            "coin": 3534,
            "dm": 236,
            "favorite": 1526,
            "like": 7488,
            "reply": 356,
            "share": 312,
            "view": 3642937
        }
    },
    {
        "id": 1587537,
        "long_title": "《不息》",
        "share_url": "https://www.bilibili.com/bangumi/play/ep1587537",
        "title": "年番新画面ED",
        "type": 2,
        "type_title": "特别花絮",
        "stat": {
            "coin": 1760,
            "dm": 232,
            "favorite": 791,
            "like": 4466,
            "reply": 354,
            "share": 163,
            "view": 1398096
        }
    },
    {
        "id": 1111885,
        "long_title": "陈楚生《天外的天》",
        "share_url": "https://www.bilibili.com/bangumi/play/ep1111885",
        "title": "牧神记OP",
        "type": 2,
        "type_title": "特别花絮",
        "stat": {
            "coin": 5567,
            "dm": 2133,
            "favorite": 3294,
            "like": 10684,
            "reply": 1250,
            "share": 1449,
            "view": 1468814
        }
    },
    {
        "id": 1113439,
        "long_title": "《不息》正式上线",
        "share_url": "https://www.bilibili.com/bangumi/play/ep1113439",
        "title": "牧神记ED",
        "type": 2,
        "type_title": "特别花絮",
        "stat": {
            "coin": 1341,
            "dm": 139,
            "favorite": 710,
            "like": 3205,
            "reply": 135,
            "share": 159,
            "view": 1210809
        }
    }
]